[ {
  "Ballast Idle" : "07:05",
  "Ballast Travel" : "11:11",
  "Ballast LNG Cost" : "444,219",
  "Ballast LNG (m³)" : "2,782",
  "Ballast LNG (mmBtu)" : "63,459",
  "Ballast Speed" : "15.7",
  "Ballast Cost" : "474,219",
  "Buy Entity" : "US",
  "Buy Inco" : "FOB",
  "Purchase Cost" : "19,380,000",
  "Buy/Start Port" : "Bonny Nigeria",
  "Buy Price" : "5.000",
  "Buy Volume" : "170,000",
  "Buy Volume (mmBtu)" : "3,876,000",
  "Cargo Type" : "Shipped",
  "D-ID" : "discharge-1 Bonny",
  "Discharge Duration" : "01:00",
  "Discharge/End Date" : "25/11/10",
  "Discharge/End Time" : "14:00",
  "Discharge Window" : "25/11/10",
  "Load/Event Duration" : "01:00",
  "Heel Cost" : "0",
  "Heel Revenue" : "0",
  "ID" : "1 Bonny",
  "L-ID" : "1 Bonny",
  "Laden Idle" : "00:00",
  "Laden Travel" : "09:08",
  "Laden LNG Cost" : "422,687",
  "Laden LNG (m³)" : "2,647",
  "Laden LNG (mmBtu)" : "60,383",
  "Laden Speed" : "19.4",
  "Laden Cost" : "452,688",
  "Load/Start Date" : "15/11/10",
  "Load/Start Time" : "07:00",
  "Load/Start Window" : "15/11/10",
  "Next event date" : "15/12/10",
  "Next event port" : "Bonny Nigeria",
  "Addn. P&L" : "0",
  "P&L (Shipping)" : "0",
  "P&L" : "6,745,291",
  "P&L (Trading)" : "6,745,291",
  "P&L (Upstream)" : "0",
  "Purchase Contract" : "HH Spot Purchase",
  "Sales Contract" : "NBP Sales",
  "Scenario" : "/scenarios/sample-data/",
  "Sell Entity" : "Europe",
  "Sell Inco" : "DES",
  "Sales Revenue" : "26,185,291",
  "Sell/End Port" : "Isle of Grain",
  "Sell Price" : "7.000",
  "Sell Volume" : "164,068",
  "Sell Volume (mmBtu)" : "3,740,755",
  "Bunker Cost" : "40,000",
  "Canal Cost" : "0",
  "Cooldown Cost" : "0",
  "Shipping Cost" : "60,000",
  "Shipping Entity" : "Shipping",
  "Hire Cost" : "0",
  "LNG Cost" : "0",
  "Other Cost" : "0",
  "Port Cost" : "20,000",
  "Total Cost" : "926,906",
  "Type" : "Cargo",
  "Vessel" : "Methane Becki Anne (170k)",
  "[P&L]" : {
    "P&L (Europe - Trading)" : "0",
    "P&L (Europe - Shipping)" : "0",
    "P&L (US - Trading)" : "6,745,291",
    "P&L (US - Shipping)" : "0"
  }
}, {
  "Ballast Idle" : "08:05",
  "Ballast Travel" : "11:11",
  "Ballast LNG Cost" : "460,179",
  "Ballast LNG (m³)" : "2,882",
  "Ballast LNG (mmBtu)" : "65,739",
  "Ballast Speed" : "15.7",
  "Ballast Cost" : "490,179",
  "Buy Entity" : "US",
  "Buy Inco" : "FOB",
  "Purchase Cost" : "19,323,000",
  "Buy/Start Port" : "Bonny Nigeria",
  "Buy Price" : "5.000",
  "Buy Volume" : "169,500",
  "Buy Volume (mmBtu)" : "3,864,600",
  "Cargo Type" : "Shipped",
  "D-ID" : "discharge-2 Bonny",
  "Discharge Duration" : "01:00",
  "Discharge/End Date" : "25/12/10",
  "Discharge/End Time" : "14:00",
  "Discharge Window" : "25/12/10",
  "Load/Event Duration" : "01:00",
  "Heel Cost" : "0",
  "Heel Revenue" : "0",
  "ID" : "2 Bonny",
  "L-ID" : "2 Bonny",
  "Laden Idle" : "00:00",
  "Laden Travel" : "09:08",
  "Laden LNG Cost" : "422,687",
  "Laden LNG (m³)" : "2,647",
  "Laden LNG (mmBtu)" : "60,383",
  "Laden Speed" : "19.4",
  "Laden Cost" : "452,688",
  "Load/Start Date" : "15/12/10",
  "Load/Start Time" : "07:00",
  "Load/Start Window" : "15/12/10",
  "Next event date" : "15/01/11",
  "Next event port" : "Bonny Nigeria",
  "Addn. P&L" : "0",
  "P&L (Shipping)" : "0",
  "P&L" : "6,786,331",
  "P&L (Trading)" : "6,786,331",
  "P&L (Upstream)" : "0",
  "Purchase Contract" : "HH Spot Purchase",
  "Sales Contract" : "NBP Sales",
  "Scenario" : "/scenarios/sample-data/",
  "Sell Entity" : "Europe",
  "Sell Inco" : "DES",
  "Sales Revenue" : "26,169,331",
  "Sell/End Port" : "Isle of Grain",
  "Sell Price" : "7.000",
  "Sell Volume" : "163,968",
  "Sell Volume (mmBtu)" : "3,738,475",
  "Bunker Cost" : "40,000",
  "Canal Cost" : "0",
  "Cooldown Cost" : "0",
  "Shipping Cost" : "60,000",
  "Shipping Entity" : "Shipping",
  "Hire Cost" : "0",
  "LNG Cost" : "0",
  "Other Cost" : "0",
  "Port Cost" : "20,000",
  "Total Cost" : "942,866",
  "Type" : "Cargo",
  "Vessel" : "Methane Becki Anne (170k)",
  "[P&L]" : {
    "P&L (Europe - Trading)" : "0",
    "P&L (Europe - Shipping)" : "0",
    "P&L (US - Trading)" : "6,786,331",
    "P&L (US - Shipping)" : "0"
  }
}, {
  "Ballast Idle" : "08:05",
  "Ballast Travel" : "11:11",
  "Ballast LNG Cost" : "460,179",
  "Ballast LNG (m³)" : "2,882",
  "Ballast LNG (mmBtu)" : "65,739",
  "Ballast Speed" : "15.7",
  "Ballast Cost" : "490,179",
  "Buy Entity" : "US",
  "Buy Inco" : "FOB",
  "Purchase Cost" : "19,323,000",
  "Buy/Start Port" : "Bonny Nigeria",
  "Buy Price" : "5.000",
  "Buy Volume" : "169,500",
  "Buy Volume (mmBtu)" : "3,864,600",
  "Cargo Type" : "Shipped",
  "D-ID" : "discharge-3 Bonny",
  "Discharge Duration" : "01:00",
  "Discharge/End Date" : "25/01/11",
  "Discharge/End Time" : "14:00",
  "Discharge Window" : "25/01/11",
  "Load/Event Duration" : "01:00",
  "Heel Cost" : "0",
  "Heel Revenue" : "0",
  "ID" : "3 Bonny",
  "L-ID" : "3 Bonny",
  "Laden Idle" : "00:00",
  "Laden Travel" : "09:08",
  "Laden LNG Cost" : "422,687",
  "Laden LNG (m³)" : "2,647",
  "Laden LNG (mmBtu)" : "60,383",
  "Laden Speed" : "19.4",
  "Laden Cost" : "452,688",
  "Load/Start Date" : "15/01/11",
  "Load/Start Time" : "07:00",
  "Load/Start Window" : "15/01/11",
  "Next event date" : "15/02/11",
  "Next event port" : "Bonny Nigeria",
  "Addn. P&L" : "0",
  "P&L (Shipping)" : "0",
  "P&L" : "6,786,331",
  "P&L (Trading)" : "6,786,331",
  "P&L (Upstream)" : "0",
  "Purchase Contract" : "HH Spot Purchase",
  "Sales Contract" : "NBP Sales",
  "Scenario" : "/scenarios/sample-data/",
  "Sell Entity" : "Europe",
  "Sell Inco" : "DES",
  "Sales Revenue" : "26,169,331",
  "Sell/End Port" : "Isle of Grain",
  "Sell Price" : "7.000",
  "Sell Volume" : "163,968",
  "Sell Volume (mmBtu)" : "3,738,475",
  "Bunker Cost" : "40,000",
  "Canal Cost" : "0",
  "Cooldown Cost" : "0",
  "Shipping Cost" : "60,000",
  "Shipping Entity" : "Shipping",
  "Hire Cost" : "0",
  "LNG Cost" : "0",
  "Other Cost" : "0",
  "Port Cost" : "20,000",
  "Total Cost" : "942,866",
  "Type" : "Cargo",
  "Vessel" : "Methane Becki Anne (170k)",
  "[P&L]" : {
    "P&L (Europe - Trading)" : "0",
    "P&L (Europe - Shipping)" : "0",
    "P&L (US - Trading)" : "6,786,331",
    "P&L (US - Shipping)" : "0"
  }
}, {
  "Ballast Idle" : "05:05",
  "Ballast Travel" : "11:11",
  "Ballast LNG Cost" : "412,299",
  "Ballast LNG (m³)" : "2,582",
  "Ballast LNG (mmBtu)" : "58,899",
  "Ballast Speed" : "15.7",
  "Ballast Cost" : "442,299",
  "Buy Entity" : "US",
  "Buy Inco" : "FOB",
  "Purchase Cost" : "19,323,000",
  "Buy/Start Port" : "Bonny Nigeria",
  "Buy Price" : "5.000",
  "Buy Volume" : "169,500",
  "Buy Volume (mmBtu)" : "3,864,600",
  "Cargo Type" : "Shipped",
  "D-ID" : "discharge-4 Bonny DES",
  "Discharge Duration" : "01:00",
  "Discharge/End Date" : "25/02/11",
  "Discharge/End Time" : "14:00",
  "Discharge Window" : "25/02/11",
  "Load/Event Duration" : "01:00",
  "Heel Cost" : "0",
  "Heel Revenue" : "0",
  "ID" : "4 Bonny",
  "L-ID" : "4 Bonny",
  "Laden Idle" : "00:00",
  "Laden Travel" : "09:08",
  "Laden LNG Cost" : "422,687",
  "Laden LNG (m³)" : "2,647",
  "Laden LNG (mmBtu)" : "60,383",
  "Laden Speed" : "19.4",
  "Laden Cost" : "452,688",
  "Load/Start Date" : "15/02/11",
  "Load/Start Time" : "07:00",
  "Load/Start Window" : "15/02/11",
  "Next event date" : "15/03/11",
  "Next event port" : "Bonny Nigeria",
  "Addn. P&L" : "0",
  "P&L (Shipping)" : "0",
  "P&L" : "6,834,211",
  "P&L (Trading)" : "6,834,211",
  "P&L (Upstream)" : "0",
  "Purchase Contract" : "HH Spot Purchase",
  "Sales Contract" : "NBP Sales",
  "Scenario" : "/scenarios/sample-data/",
  "Sell Entity" : "Europe",
  "Sell Inco" : "DES",
  "Sales Revenue" : "26,217,211",
  "Sell/End Port" : "Isle of Grain",
  "Sell Price" : "7.000",
  "Sell Volume" : "164,268",
  "Sell Volume (mmBtu)" : "3,745,315",
  "Bunker Cost" : "40,000",
  "Canal Cost" : "0",
  "Cooldown Cost" : "0",
  "Shipping Cost" : "60,000",
  "Shipping Entity" : "Shipping",
  "Hire Cost" : "0",
  "LNG Cost" : "0",
  "Other Cost" : "0",
  "Port Cost" : "20,000",
  "Total Cost" : "894,986",
  "Type" : "Cargo",
  "Vessel" : "Methane Becki Anne (170k)",
  "[P&L]" : {
    "P&L (Europe - Trading)" : "0",
    "P&L (Europe - Shipping)" : "0",
    "P&L (US - Trading)" : "6,834,211",
    "P&L (US - Shipping)" : "0"
  }
}, {
  "Ballast Idle" : "07:02",
  "Ballast Travel" : "10:19",
  "Ballast LNG Cost" : "423,072",
  "Ballast LNG (m³)" : "2,650",
  "Ballast LNG (mmBtu)" : "60,438",
  "Ballast Speed" : "15.7",
  "Ballast Cost" : "453,072",
  "Buy Entity" : "US",
  "Buy Inco" : "FOB",
  "Purchase Cost" : "19,323,000",
  "Buy/Start Port" : "Bonny Nigeria",
  "Buy Price" : "5.000",
  "Buy Volume" : "169,500",
  "Buy Volume (mmBtu)" : "3,864,600",
  "Cargo Type" : "Shipped",
  "D-ID" : "discharge-5 Bonny",
  "Discharge Duration" : "01:00",
  "Discharge/End Date" : "25/03/11",
  "Discharge/End Time" : "14:00",
  "Discharge Window" : "25/03/11",
  "Load/Event Duration" : "01:00",
  "Heel Cost" : "0",
  "Heel Revenue" : "0",
  "ID" : "5 Bonny",
  "L-ID" : "5 Bonny",
  "Laden Idle" : "00:00",
  "Laden Travel" : "09:08",
  "Laden LNG Cost" : "422,687",
  "Laden LNG (m³)" : "2,647",
  "Laden LNG (mmBtu)" : "60,383",
  "Laden Speed" : "19.4",
  "Laden Cost" : "452,688",
  "Load/Start Date" : "15/03/11",
  "Load/Start Time" : "07:00",
  "Load/Start Window" : "15/03/11",
  "Next event date" : "13/04/11",
  "Next event port" : "Point Fortin",
  "Addn. P&L" : "0",
  "P&L (Shipping)" : "0",
  "P&L" : "6,823,438",
  "P&L (Trading)" : "6,823,438",
  "P&L (Upstream)" : "0",
  "Purchase Contract" : "HH Spot Purchase",
  "Sales Contract" : "NBP Sales",
  "Scenario" : "/scenarios/sample-data/",
  "Sell Entity" : "Europe",
  "Sell Inco" : "DES",
  "Sales Revenue" : "26,206,438",
  "Sell/End Port" : "Isle of Grain",
  "Sell Price" : "7.000",
  "Sell Volume" : "164,200",
  "Sell Volume (mmBtu)" : "3,743,776",
  "Bunker Cost" : "40,000",
  "Canal Cost" : "0",
  "Cooldown Cost" : "0",
  "Shipping Cost" : "60,000",
  "Shipping Entity" : "Shipping",
  "Hire Cost" : "0",
  "LNG Cost" : "0",
  "Other Cost" : "0",
  "Port Cost" : "20,000",
  "Total Cost" : "905,759",
  "Type" : "Cargo",
  "Vessel" : "Methane Becki Anne (170k)",
  "[P&L]" : {
    "P&L (Europe - Trading)" : "0",
    "P&L (Europe - Shipping)" : "0",
    "P&L (US - Trading)" : "6,823,438",
    "P&L (US - Shipping)" : "0"
  }
}, {
  "Ballast Idle" : "07:06",
  "Ballast Travel" : "11:11",
  "Ballast LNG Cost" : "444,885",
  "Ballast LNG (m³)" : "2,787",
  "Ballast LNG (mmBtu)" : "63,555",
  "Ballast Speed" : "15.7",
  "Ballast Cost" : "474,885",
  "Buy Entity" : "US",
  "Buy Inco" : "FOB",
  "Purchase Cost" : "19,323,000",
  "Buy/Start Port" : "Bonny Nigeria",
  "Buy Price" : "5.000",
  "Buy Volume" : "169,500",
  "Buy Volume (mmBtu)" : "3,864,600",
  "Cargo Type" : "Shipped",
  "D-ID" : "discharge-6 Bonny",
  "Discharge Duration" : "01:00",
  "Discharge/End Date" : "25/04/11",
  "Discharge/End Time" : "14:00",
  "Discharge Window" : "25/04/11",
  "Load/Event Duration" : "01:00",
  "Heel Cost" : "0",
  "Heel Revenue" : "0",
  "ID" : "6 Bonny",
  "L-ID" : "6 Bonny",
  "Laden Idle" : "00:00",
  "Laden Travel" : "09:07",
  "Laden LNG Cost" : "426,994",
  "Laden LNG (m³)" : "2,675",
  "Laden LNG (mmBtu)" : "60,998",
  "Laden Speed" : "19.5",
  "Laden Cost" : "456,994",
  "Load/Start Date" : "15/04/11",
  "Load/Start Time" : "07:00",
  "Load/Start Window" : "15/04/11",
  "Next event date" : "15/05/11",
  "Next event port" : "Bonny Nigeria",
  "Addn. P&L" : "0",
  "P&L (Shipping)" : "0",
  "P&L" : "6,797,320",
  "P&L (Trading)" : "6,797,320",
  "P&L (Upstream)" : "0",
  "Purchase Contract" : "HH Spot Purchase",
  "Sales Contract" : "NBP Sales",
  "Scenario" : "/scenarios/sample-data/",
  "Sell Entity" : "Europe",
  "Sell Inco" : "DES",
  "Sales Revenue" : "26,180,320",
  "Sell/End Port" : "Isle of Grain",
  "Sell Price" : "7.000",
  "Sell Volume" : "164,037",
  "Sell Volume (mmBtu)" : "3,740,045",
  "Bunker Cost" : "40,000",
  "Canal Cost" : "0",
  "Cooldown Cost" : "0",
  "Shipping Cost" : "60,000",
  "Shipping Entity" : "Shipping",
  "Hire Cost" : "0",
  "LNG Cost" : "0",
  "Other Cost" : "0",
  "Port Cost" : "20,000",
  "Total Cost" : "931,879",
  "Type" : "Cargo",
  "Vessel" : "Methane Julia Louise (170k)",
  "[P&L]" : {
    "P&L (Europe - Trading)" : "0",
    "P&L (Europe - Shipping)" : "0",
    "P&L (US - Trading)" : "6,797,320",
    "P&L (US - Shipping)" : "0"
  }
}, {
  "Ballast Idle" : "00:10",
  "Ballast Travel" : "10:19",
  "Ballast LNG Cost" : "316,672",
  "Ballast LNG (m³)" : "1,983",
  "Ballast LNG (mmBtu)" : "45,238",
  "Ballast Speed" : "15.7",
  "Ballast Cost" : "346,672",
  "Buy Entity" : "US",
  "Buy Inco" : "FOB",
  "Purchase Cost" : "19,323,000",
  "Buy/Start Port" : "Bonny Nigeria",
  "Buy Price" : "5.000",
  "Buy Volume" : "169,500",
  "Buy Volume (mmBtu)" : "3,864,600",
  "Cargo Type" : "Shipped",
  "D-ID" : "discharge-7 Bonny",
  "Discharge Duration" : "01:00",
  "Discharge/End Date" : "25/05/11",
  "Discharge/End Time" : "14:00",
  "Discharge Window" : "25/05/11",
  "Load/Event Duration" : "01:00",
  "Heel Cost" : "0",
  "Heel Revenue" : "0",
  "ID" : "7 Bonny",
  "L-ID" : "7 Bonny",
  "Laden Idle" : "00:00",
  "Laden Travel" : "09:07",
  "Laden LNG Cost" : "426,994",
  "Laden LNG (m³)" : "2,675",
  "Laden LNG (mmBtu)" : "60,998",
  "Laden Speed" : "19.5",
  "Laden Cost" : "456,994",
  "Load/Start Date" : "15/05/11",
  "Load/Start Time" : "07:00",
  "Load/Start Window" : "15/05/11",
  "Next event date" : "06/06/11",
  "Next event port" : "Point Fortin",
  "Addn. P&L" : "0",
  "P&L (Shipping)" : "0",
  "P&L" : "6,925,532",
  "P&L (Trading)" : "6,925,532",
  "P&L (Upstream)" : "0",
  "Purchase Contract" : "HH Spot Purchase",
  "Sales Contract" : "NBP Sales",
  "Scenario" : "/scenarios/sample-data/",
  "Sell Entity" : "Europe",
  "Sell Inco" : "DES",
  "Sales Revenue" : "26,308,532",
  "Sell/End Port" : "Isle of Grain",
  "Sell Price" : "7.000",
  "Sell Volume" : "164,840",
  "Sell Volume (mmBtu)" : "3,758,361",
  "Bunker Cost" : "40,000",
  "Canal Cost" : "0",
  "Cooldown Cost" : "0",
  "Shipping Cost" : "60,000",
  "Shipping Entity" : "Shipping",
  "Hire Cost" : "0",
  "LNG Cost" : "0",
  "Other Cost" : "0",
  "Port Cost" : "20,000",
  "Total Cost" : "803,666",
  "Type" : "Cargo",
  "Vessel" : "Methane Julia Louise (170k)",
  "[P&L]" : {
    "P&L (Europe - Trading)" : "0",
    "P&L (Europe - Shipping)" : "0",
    "P&L (US - Trading)" : "6,925,532",
    "P&L (US - Shipping)" : "0"
  }
}, {
  "Charter Rate" : "150,000",
  "Ballast Idle" : "50:18",
  "Ballast Travel" : "11:11",
  "Ballast LNG Cost" : "1,139,145",
  "Ballast LNG (m³)" : "7,137",
  "Ballast LNG (mmBtu)" : "162,735",
  "Ballast Speed" : "15.7",
  "Ballast Cost" : "10,650,395",
  "Buy Entity" : "US",
  "Buy Inco" : "FOB",
  "Purchase Cost" : "19,323,000",
  "Buy/Start Port" : "Bonny Nigeria",
  "Buy Price" : "5.000",
  "Buy Volume" : "169,500",
  "Buy Volume (mmBtu)" : "3,864,600",
  "Cargo Type" : "Shipped",
  "D-ID" : "discharge-8 Bonny",
  "Discharge Duration" : "01:00",
  "Discharge/End Date" : "25/06/11",
  "Discharge/End Time" : "14:00",
  "Discharge Window" : "25/06/11",
  "Load/Event Duration" : "01:00",
  "Heel Cost" : "0",
  "Heel Revenue" : "0",
  "ID" : "8 Bonny",
  "L-ID" : "8 Bonny",
  "Laden Idle" : "00:00",
  "Laden Travel" : "09:07",
  "Laden LNG Cost" : "426,994",
  "Laden LNG (m³)" : "2,675",
  "Laden LNG (mmBtu)" : "60,998",
  "Laden Speed" : "19.5",
  "Laden Cost" : "2,000,744",
  "Load/Start Date" : "15/06/11",
  "Load/Start Time" : "07:00",
  "Load/Start Window" : "15/06/11",
  "Next event date" : "27/08/11",
  "Next event port" : "Bonny Nigeria",
  "Addn. P&L" : "0",
  "P&L (Shipping)" : "0",
  "P&L" : "-4,842,139",
  "P&L (Trading)" : "-4,842,139",
  "P&L (Upstream)" : "0",
  "Purchase Contract" : "HH Spot Purchase",
  "Sales Contract" : "NBP Sales",
  "Scenario" : "/scenarios/sample-data/",
  "Sell Entity" : "Europe",
  "Sell Inco" : "DES",
  "Sales Revenue" : "25,565,860",
  "Sell/End Port" : "Isle of Grain",
  "Sell Price" : "7.000",
  "Sell Volume" : "160,187",
  "Sell Volume (mmBtu)" : "3,652,265",
  "Bunker Cost" : "40,000",
  "Canal Cost" : "0",
  "Cooldown Cost" : "0",
  "Shipping Cost" : "11,085,000",
  "Shipping Entity" : "Shipping",
  "Hire Cost" : "11,025,000",
  "LNG Cost" : "0",
  "Other Cost" : "0",
  "Port Cost" : "20,000",
  "Total Cost" : "12,651,139",
  "Type" : "Cargo",
  "Vessel" : "Charter Ship (170k)",
  "[P&L]" : {
    "P&L (Europe - Trading)" : "0",
    "P&L (Europe - Shipping)" : "0",
    "P&L (US - Trading)" : "-4,842,139",
    "P&L (US - Shipping)" : "0"
  }
}, {
  "Charter Rate" : "99,999",
  "Ballast Idle" : "00:11",
  "Ballast LNG Cost" : "0",
  "Ballast LNG (m³)" : "0",
  "Ballast LNG (mmBtu)" : "0",
  "Ballast Cost" : "68,749",
  "Buy/Start Port" : "Point Fortin",
  "Discharge/End Date" : "01/01/11",
  "Discharge/End Time" : "20:00",
  "Load/Event Duration" : "00:00",
  "Heel Cost" : "0",
  "Heel Revenue" : "0",
  "ID" : "Bluesky",
  "L-ID" : "Bluesky",
  "Load/Start Date" : "01/01/11",
  "Load/Start Time" : "20:00",
  "Next event date" : "02/01/11",
  "Next event port" : "Point Fortin",
  "Addn. P&L" : "0",
  "P&L (Shipping)" : "-68,749",
  "P&L" : "-68,749",
  "P&L (Trading)" : "0",
  "P&L (Upstream)" : "0",
  "Scenario" : "/scenarios/sample-data/",
  "Bunker Cost" : "22,916",
  "Canal Cost" : "0",
  "Cooldown Cost" : "0",
  "Shipping Cost" : "68,749",
  "Shipping Entity" : "Shipping",
  "Hire Cost" : "45,833",
  "LNG Cost" : "0",
  "Other Cost" : "0",
  "Port Cost" : "0",
  "Total Cost" : "68,749",
  "Type" : "Start",
  "Vessel" : "Bluesky (145k)",
  "[P&L]" : {
    "P&L (Shipping - Trading)" : "0",
    "P&L (Shipping - Shipping)" : "-68,749"
  }
}, {
  "Charter Rate" : "100,000",
  "Ballast Idle" : "00:00",
  "Ballast LNG Cost" : "0",
  "Ballast LNG (m³)" : "0",
  "Ballast LNG (mmBtu)" : "0",
  "Ballast Cost" : "2,329,166",
  "Buy/Start Port" : "Point Fortin",
  "Discharge/End Date" : "24/12/10",
  "Discharge/End Time" : "14:00",
  "Load/Event Duration" : "23:07",
  "Heel Cost" : "0",
  "Heel Revenue" : "0",
  "ID" : "Charter Out -  Start Methane Princess",
  "L-ID" : "Charter Out -  Start Methane Princess",
  "Load/Start Date" : "01/12/10",
  "Load/Start Time" : "07:00",
  "Next event date" : "24/12/10",
  "Next event port" : "Point Fortin",
  "Addn. P&L" : "0",
  "P&L (Shipping)" : "0",
  "P&L" : "0",
  "P&L (Trading)" : "0",
  "P&L (Upstream)" : "0",
  "Scenario" : "/scenarios/sample-data/",
  "Bunker Cost" : "0",
  "Canal Cost" : "0",
  "Cooldown Cost" : "0",
  "Shipping Cost" : "2,329,166",
  "Shipping Entity" : "Shipping",
  "Hire Cost" : "2,329,166",
  "LNG Cost" : "0",
  "Other Cost" : "0",
  "Port Cost" : "0",
  "Total Cost" : "0",
  "Type" : "Charter Out (virt)",
  "Vessel" : "Methane Princess (138k)",
  "[P&L]" : {
    "P&L (Shipping - Trading)" : "0",
    "P&L (Shipping - Shipping)" : "0"
  }
}, {
  "Charter Rate" : "100,000",
  "Ballast Idle" : "00:00",
  "Ballast LNG Cost" : "0",
  "Ballast LNG (m³)" : "0",
  "Ballast LNG (mmBtu)" : "0",
  "Ballast Cost" : "2,712,500",
  "Buy/Start Port" : "Damietta",
  "Discharge/End Date" : "03/06/11",
  "Discharge/End Time" : "14:00",
  "Load/Event Duration" : "27:03",
  "Heel Cost" : "0",
  "Heel Revenue" : "0",
  "ID" : "Charter Out - discharge-cargo-16",
  "L-ID" : "Charter Out - discharge-cargo-16",
  "Load/Start Date" : "07/05/11",
  "Load/Start Time" : "11:00",
  "Next event date" : "03/06/11",
  "Next event port" : "Damietta",
  "Addn. P&L" : "0",
  "P&L (Shipping)" : "0",
  "P&L" : "0",
  "P&L (Trading)" : "0",
  "P&L (Upstream)" : "0",
  "Scenario" : "/scenarios/sample-data/",
  "Bunker Cost" : "0",
  "Canal Cost" : "0",
  "Cooldown Cost" : "0",
  "Shipping Cost" : "2,712,500",
  "Shipping Entity" : "Shipping",
  "Hire Cost" : "2,712,500",
  "LNG Cost" : "0",
  "Other Cost" : "0",
  "Port Cost" : "0",
  "Total Cost" : "0",
  "Type" : "Charter Out (virt)",
  "Vessel" : "Methane Princess (138k)",
  "[P&L]" : {
    "P&L (Shipping - Trading)" : "0",
    "P&L (Shipping - Shipping)" : "0"
  }
}, {
  "Charter Rate" : "100,000",
  "Ballast Idle" : "00:00",
  "Ballast LNG Cost" : "0",
  "Ballast LNG (m³)" : "0",
  "Ballast LNG (mmBtu)" : "0",
  "Ballast Cost" : "4,775,000",
  "Buy/Start Port" : "Damietta",
  "Discharge/End Date" : "27/08/11",
  "Discharge/End Time" : "20:00",
  "Load/Event Duration" : "47:18",
  "Heel Cost" : "0",
  "Heel Revenue" : "0",
  "ID" : "Charter Out - discharge-cargo-20",
  "L-ID" : "Charter Out - discharge-cargo-20",
  "Load/Start Date" : "11/07/11",
  "Load/Start Time" : "02:00",
  "Next event date" : "27/08/11",
  "Next event port" : "Damietta",
  "Addn. P&L" : "0",
  "P&L (Shipping)" : "0",
  "P&L" : "0",
  "P&L (Trading)" : "0",
  "P&L (Upstream)" : "0",
  "Scenario" : "/scenarios/sample-data/",
  "Bunker Cost" : "0",
  "Canal Cost" : "0",
  "Cooldown Cost" : "0",
  "Shipping Cost" : "4,775,000",
  "Shipping Entity" : "Shipping",
  "Hire Cost" : "4,775,000",
  "LNG Cost" : "0",
  "Other Cost" : "0",
  "Port Cost" : "0",
  "Total Cost" : "0",
  "Type" : "Charter Out (virt)",
  "Vessel" : "Methane Princess (138k)",
  "[P&L]" : {
    "P&L (Shipping - Trading)" : "0",
    "P&L (Shipping - Shipping)" : "0"
  }
}, {
  "Charter Rate" : "100,000",
  "Ballast Idle" : "00:00",
  "Ballast LNG Cost" : "0",
  "Ballast LNG (m³)" : "0",
  "Ballast LNG (mmBtu)" : "0",
  "Ballast Cost" : "1,766,666",
  "Buy/Start Port" : "Punta Europa LNG",
  "Discharge/End Date" : "08/04/11",
  "Discharge/End Time" : "14:00",
  "Load/Event Duration" : "17:16",
  "Heel Cost" : "0",
  "Heel Revenue" : "0",
  "ID" : "Charter Out - discharge-cargo-31",
  "L-ID" : "Charter Out - discharge-cargo-31",
  "Load/Start Date" : "21/03/11",
  "Load/Start Time" : "22:00",
  "Next event date" : "08/04/11",
  "Next event port" : "Punta Europa LNG",
  "Addn. P&L" : "0",
  "P&L (Shipping)" : "0",
  "P&L" : "0",
  "P&L (Trading)" : "0",
  "P&L (Upstream)" : "0",
  "Scenario" : "/scenarios/sample-data/",
  "Bunker Cost" : "0",
  "Canal Cost" : "0",
  "Cooldown Cost" : "0",
  "Shipping Cost" : "1,766,666",
  "Shipping Entity" : "Shipping",
  "Hire Cost" : "1,766,666",
  "LNG Cost" : "0",
  "Other Cost" : "0",
  "Port Cost" : "0",
  "Total Cost" : "0",
  "Type" : "Charter Out (virt)",
  "Vessel" : "Methane Princess (138k)",
  "[P&L]" : {
    "P&L (Shipping - Trading)" : "0",
    "P&L (Shipping - Shipping)" : "0"
  }
}, {
  "Charter Rate" : "150,000",
  "Ballast Idle" : "41:01",
  "Ballast LNG Cost" : "0",
  "Ballast LNG (m³)" : "4,104",
  "Ballast LNG (mmBtu)" : "92,343",
  "Ballast Cost" : "6,156,250",
  "Buy/Start Port" : "Punta Europa LNG",
  "Discharge/End Date" : "20/11/10",
  "Discharge/End Time" : "13:00",
  "Load/Event Duration" : "00:00",
  "Heel Cost" : "0",
  "Heel Revenue" : "0",
  "ID" : "Charter Ship",
  "L-ID" : "Charter Ship",
  "Load/Start Date" : "20/11/10",
  "Load/Start Time" : "13:00",
  "Next event date" : "31/12/10",
  "Next event port" : "Punta Europa LNG",
  "Addn. P&L" : "0",
  "P&L (Shipping)" : "-6,156,250",
  "P&L" : "-6,156,250",
  "P&L (Trading)" : "0",
  "P&L (Upstream)" : "0",
  "Scenario" : "/scenarios/sample-data/",
  "Bunker Cost" : "0",
  "Canal Cost" : "0",
  "Cooldown Cost" : "0",
  "Shipping Cost" : "6,156,250",
  "Shipping Entity" : "Shipping",
  "Hire Cost" : "6,156,250",
  "LNG Cost" : "0",
  "Other Cost" : "0",
  "Port Cost" : "0",
  "Total Cost" : "6,156,250",
  "Type" : "Start",
  "Vessel" : "Charter Ship (170k)",
  "[P&L]" : {
    "P&L (Shipping - Trading)" : "0",
    "P&L (Shipping - Shipping)" : "-6,156,250"
  }
}, {
  "Ballast Idle" : "01:00",
  "Ballast LNG Cost" : "0",
  "Ballast LNG (m³)" : "0",
  "Ballast LNG (mmBtu)" : "0",
  "Ballast Cost" : "50,000",
  "Buy/Start Port" : "Damietta",
  "Discharge/End Date" : "22/03/11",
  "Discharge/End Time" : "07:00",
  "Load/Event Duration" : "30:00",
  "Heel Cost" : "0",
  "Heel Revenue" : "0",
  "ID" : "Dry Dock",
  "L-ID" : "Dry Dock",
  "Load/Start Date" : "20/02/11",
  "Load/Start Time" : "07:00",
  "Load/Start Window" : "10/02/11",
  "Next event date" : "23/03/11",
  "Next event port" : "Damietta",
  "Addn. P&L" : "0",
  "P&L (Shipping)" : "-253,604",
  "P&L" : "-253,604",
  "P&L (Trading)" : "0",
  "P&L (Upstream)" : "0",
  "Scenario" : "/scenarios/sample-data/",
  "Sell/End Port" : "Damietta",
  "Bunker Cost" : "50,000",
  "Canal Cost" : "0",
  "Cooldown Cost" : "203,604",
  "Shipping Cost" : "253,604",
  "Shipping Entity" : "Shipping",
  "Hire Cost" : "0",
  "LNG Cost" : "0",
  "Other Cost" : "0",
  "Port Cost" : "0",
  "Total Cost" : "253,604",
  "Type" : "Dry Dock",
  "Vessel" : "Methane Heather Sally (149k)",
  "[P&L]" : {
    "P&L (Shipping - Trading)" : "0",
    "P&L (Shipping - Shipping)" : "-253,604"
  }
}, {
  "Buy/Start Port" : "Punta Europa LNG",
  "Discharge/End Date" : "27/08/11",
  "Discharge/End Time" : "19:00",
  "Load/Event Duration" : "00:00",
  "Heel Cost" : "0",
  "Heel Revenue" : "0",
  "ID" : "End Bluesky",
  "L-ID" : "End Bluesky",
  "Load/Start Date" : "27/08/11",
  "Load/Start Time" : "19:00",
  "Addn. P&L" : "0",
  "P&L (Shipping)" : "0",
  "P&L" : "0",
  "P&L (Trading)" : "0",
  "P&L (Upstream)" : "0",
  "Scenario" : "/scenarios/sample-data/",
  "Bunker Cost" : "0",
  "Canal Cost" : "0",
  "Cooldown Cost" : "0",
  "Shipping Cost" : "0",
  "Shipping Entity" : "Shipping",
  "Hire Cost" : "0",
  "LNG Cost" : "0",
  "Other Cost" : "0",
  "Port Cost" : "0",
  "Total Cost" : "0",
  "Type" : "End",
  "Vessel" : "Bluesky (145k)",
  "[P&L]" : {
    "P&L (Shipping - Trading)" : "0",
    "P&L (Shipping - Shipping)" : "0"
  }
}, {
  "Buy/Start Port" : "Bonny Nigeria",
  "Discharge/End Date" : "27/08/11",
  "Discharge/End Time" : "19:00",
  "Load/Event Duration" : "00:00",
  "Heel Cost" : "0",
  "Heel Revenue" : "0",
  "ID" : "End Charter Ship",
  "L-ID" : "End Charter Ship",
  "Load/Start Date" : "27/08/11",
  "Load/Start Time" : "19:00",
  "Addn. P&L" : "0",
  "P&L (Shipping)" : "0",
  "P&L" : "0",
  "P&L (Trading)" : "0",
  "P&L (Upstream)" : "0",
  "Scenario" : "/scenarios/sample-data/",
  "Bunker Cost" : "0",
  "Canal Cost" : "0",
  "Cooldown Cost" : "0",
  "Shipping Cost" : "0",
  "Shipping Entity" : "Shipping",
  "Hire Cost" : "0",
  "LNG Cost" : "0",
  "Other Cost" : "0",
  "Port Cost" : "0",
  "Total Cost" : "0",
  "Type" : "End",
  "Vessel" : "Charter Ship (170k)",
  "[P&L]" : {
    "P&L (Shipping - Trading)" : "0",
    "P&L (Shipping - Shipping)" : "0"
  }
}, {
  "Buy/Start Port" : "Punta Europa LNG",
  "Discharge/End Date" : "27/08/11",
  "Discharge/End Time" : "19:00",
  "Load/Event Duration" : "00:00",
  "Heel Cost" : "0",
  "Heel Revenue" : "0",
  "ID" : "End Methane Becki Anne",
  "L-ID" : "End Methane Becki Anne",
  "Load/Start Date" : "27/08/11",
  "Load/Start Time" : "19:00",
  "Addn. P&L" : "0",
  "P&L (Shipping)" : "0",
  "P&L" : "0",
  "P&L (Trading)" : "0",
  "P&L (Upstream)" : "0",
  "Scenario" : "/scenarios/sample-data/",
  "Bunker Cost" : "0",
  "Canal Cost" : "0",
  "Cooldown Cost" : "0",
  "Shipping Cost" : "0",
  "Shipping Entity" : "Shipping",
  "Hire Cost" : "0",
  "LNG Cost" : "0",
  "Other Cost" : "0",
  "Port Cost" : "0",
  "Total Cost" : "0",
  "Type" : "End",
  "Vessel" : "Methane Becki Anne (170k)",
  "[P&L]" : {
    "P&L (Shipping - Trading)" : "0",
    "P&L (Shipping - Shipping)" : "0"
  }
}, {
  "Buy/Start Port" : "Point Fortin",
  "Discharge/End Date" : "27/08/11",
  "Discharge/End Time" : "14:00",
  "Load/Event Duration" : "00:00",
  "Heel Cost" : "0",
  "Heel Revenue" : "0",
  "ID" : "End Methane Heather Sally",
  "L-ID" : "End Methane Heather Sally",
  "Load/Start Date" : "27/08/11",
  "Load/Start Time" : "14:00",
  "Addn. P&L" : "0",
  "P&L (Shipping)" : "0",
  "P&L" : "0",
  "P&L (Trading)" : "0",
  "P&L (Upstream)" : "0",
  "Scenario" : "/scenarios/sample-data/",
  "Bunker Cost" : "0",
  "Canal Cost" : "0",
  "Cooldown Cost" : "0",
  "Shipping Cost" : "0",
  "Shipping Entity" : "Shipping",
  "Hire Cost" : "0",
  "LNG Cost" : "0",
  "Other Cost" : "0",
  "Port Cost" : "0",
  "Total Cost" : "0",
  "Type" : "End",
  "Vessel" : "Methane Heather Sally (149k)",
  "[P&L]" : {
    "P&L (Shipping - Trading)" : "0",
    "P&L (Shipping - Shipping)" : "0"
  }
}, {
  "Buy/Start Port" : "Point Fortin",
  "Discharge/End Date" : "27/08/11",
  "Discharge/End Time" : "14:00",
  "Load/Event Duration" : "00:00",
  "Heel Cost" : "0",
  "Heel Revenue" : "0",
  "ID" : "End Methane Julia Louise",
  "L-ID" : "End Methane Julia Louise",
  "Load/Start Date" : "27/08/11",
  "Load/Start Time" : "14:00",
  "Addn. P&L" : "0",
  "P&L (Shipping)" : "0",
  "P&L" : "0",
  "P&L (Trading)" : "0",
  "P&L (Upstream)" : "0",
  "Scenario" : "/scenarios/sample-data/",
  "Bunker Cost" : "0",
  "Canal Cost" : "0",
  "Cooldown Cost" : "0",
  "Shipping Cost" : "0",
  "Shipping Entity" : "Shipping",
  "Hire Cost" : "0",
  "LNG Cost" : "0",
  "Other Cost" : "0",
  "Port Cost" : "0",
  "Total Cost" : "0",
  "Type" : "End",
  "Vessel" : "Methane Julia Louise (170k)",
  "[P&L]" : {
    "P&L (Shipping - Trading)" : "0",
    "P&L (Shipping - Shipping)" : "0"
  }
}, {
  "Buy/Start Port" : "Punta Europa LNG",
  "Discharge/End Date" : "27/08/11",
  "Discharge/End Time" : "19:00",
  "Load/Event Duration" : "00:00",
  "Heel Cost" : "0",
  "Heel Revenue" : "0",
  "ID" : "End Methane Lydon Volney",
  "L-ID" : "End Methane Lydon Volney",
  "Load/Start Date" : "27/08/11",
  "Load/Start Time" : "19:00",
  "Addn. P&L" : "0",
  "P&L (Shipping)" : "0",
  "P&L" : "0",
  "P&L (Trading)" : "0",
  "P&L (Upstream)" : "0",
  "Scenario" : "/scenarios/sample-data/",
  "Bunker Cost" : "0",
  "Canal Cost" : "0",
  "Cooldown Cost" : "0",
  "Shipping Cost" : "0",
  "Shipping Entity" : "Shipping",
  "Hire Cost" : "0",
  "LNG Cost" : "0",
  "Other Cost" : "0",
  "Port Cost" : "0",
  "Total Cost" : "0",
  "Type" : "End",
  "Vessel" : "Methane Lydon Volney (149k)",
  "[P&L]" : {
    "P&L (Shipping - Trading)" : "0",
    "P&L (Shipping - Shipping)" : "0"
  }
}, {
  "Buy/Start Port" : "Damietta",
  "Discharge/End Date" : "27/08/11",
  "Discharge/End Time" : "20:00",
  "Load/Event Duration" : "00:00",
  "Heel Cost" : "0",
  "Heel Revenue" : "0",
  "ID" : "End Methane Princess",
  "L-ID" : "End Methane Princess",
  "Load/Start Date" : "27/08/11",
  "Load/Start Time" : "20:00",
  "Addn. P&L" : "0",
  "P&L (Shipping)" : "0",
  "P&L" : "0",
  "P&L (Trading)" : "0",
  "P&L (Upstream)" : "0",
  "Scenario" : "/scenarios/sample-data/",
  "Bunker Cost" : "0",
  "Canal Cost" : "0",
  "Cooldown Cost" : "0",
  "Shipping Cost" : "0",
  "Shipping Entity" : "Shipping",
  "Hire Cost" : "0",
  "LNG Cost" : "0",
  "Other Cost" : "0",
  "Port Cost" : "0",
  "Total Cost" : "0",
  "Type" : "End",
  "Vessel" : "Methane Princess (138k)",
  "[P&L]" : {
    "P&L (Shipping - Trading)" : "0",
    "P&L (Shipping - Shipping)" : "0"
  }
}, {
  "Ballast Idle" : "00:00",
  "Ballast LNG Cost" : "0",
  "Ballast LNG (m³)" : "0",
  "Ballast LNG (mmBtu)" : "0",
  "Ballast Cost" : "0",
  "Buy/Start Port" : "Bonny Nigeria",
  "Discharge/End Date" : "15/11/10",
  "Discharge/End Time" : "07:00",
  "Load/Event Duration" : "00:00",
  "Heel Cost" : "0",
  "Heel Revenue" : "0",
  "ID" : "Methane Becki Anne",
  "L-ID" : "Methane Becki Anne",
  "Load/Start Date" : "15/11/10",
  "Load/Start Time" : "07:00",
  "Next event date" : "15/11/10",
  "Next event port" : "Bonny Nigeria",
  "Addn. P&L" : "0",
  "P&L (Shipping)" : "0",
  "P&L" : "0",
  "P&L (Trading)" : "0",
  "P&L (Upstream)" : "0",
  "Scenario" : "/scenarios/sample-data/",
  "Bunker Cost" : "0",
  "Canal Cost" : "0",
  "Cooldown Cost" : "0",
  "Shipping Cost" : "0",
  "Shipping Entity" : "Shipping",
  "Hire Cost" : "0",
  "LNG Cost" : "0",
  "Other Cost" : "0",
  "Port Cost" : "0",
  "Total Cost" : "0",
  "Type" : "Start",
  "Vessel" : "Methane Becki Anne (170k)",
  "[P&L]" : {
    "P&L (Shipping - Trading)" : "0",
    "P&L (Shipping - Shipping)" : "0"
  }
}, {
  "Ballast Idle" : "00:01",
  "Ballast LNG Cost" : "0",
  "Ballast LNG (m³)" : "0",
  "Ballast LNG (mmBtu)" : "0",
  "Ballast Cost" : "2,083",
  "Buy/Start Port" : "Punta Europa LNG",
  "Discharge/End Date" : "29/11/10",
  "Discharge/End Time" : "06:00",
  "Load/Event Duration" : "00:00",
  "Heel Cost" : "0",
  "Heel Revenue" : "0",
  "ID" : "Methane Heather Sally",
  "L-ID" : "Methane Heather Sally",
  "Load/Start Date" : "29/11/10",
  "Load/Start Time" : "06:00",
  "Next event date" : "29/11/10",
  "Next event port" : "Punta Europa LNG",
  "Addn. P&L" : "0",
  "P&L (Shipping)" : "-2,083",
  "P&L" : "-2,083",
  "P&L (Trading)" : "0",
  "P&L (Upstream)" : "0",
  "Scenario" : "/scenarios/sample-data/",
  "Bunker Cost" : "2,083",
  "Canal Cost" : "0",
  "Cooldown Cost" : "0",
  "Shipping Cost" : "2,083",
  "Shipping Entity" : "Shipping",
  "Hire Cost" : "0",
  "LNG Cost" : "0",
  "Other Cost" : "0",
  "Port Cost" : "0",
  "Total Cost" : "2,083",
  "Type" : "Start",
  "Vessel" : "Methane Heather Sally (149k)",
  "[P&L]" : {
    "P&L (Shipping - Trading)" : "0",
    "P&L (Shipping - Shipping)" : "-2,083"
  }
}, {
  "Ballast Idle" : "00:00",
  "Ballast LNG Cost" : "0",
  "Ballast LNG (m³)" : "0",
  "Ballast LNG (mmBtu)" : "0",
  "Ballast Cost" : "0",
  "Buy/Start Port" : "Punta Europa LNG",
  "Discharge/End Date" : "21/12/10",
  "Discharge/End Time" : "14:00",
  "Load/Event Duration" : "00:00",
  "Heel Cost" : "0",
  "Heel Revenue" : "0",
  "ID" : "Methane Julia Louise",
  "L-ID" : "Methane Julia Louise",
  "Load/Start Date" : "21/12/10",
  "Load/Start Time" : "14:00",
  "Next event date" : "21/12/10",
  "Next event port" : "Punta Europa LNG",
  "Addn. P&L" : "0",
  "P&L (Shipping)" : "0",
  "P&L" : "0",
  "P&L (Trading)" : "0",
  "P&L (Upstream)" : "0",
  "Scenario" : "/scenarios/sample-data/",
  "Bunker Cost" : "0",
  "Canal Cost" : "0",
  "Cooldown Cost" : "0",
  "Shipping Cost" : "0",
  "Shipping Entity" : "Shipping",
  "Hire Cost" : "0",
  "LNG Cost" : "0",
  "Other Cost" : "0",
  "Port Cost" : "0",
  "Total Cost" : "0",
  "Type" : "Start",
  "Vessel" : "Methane Julia Louise (170k)",
  "[P&L]" : {
    "P&L (Shipping - Trading)" : "0",
    "P&L (Shipping - Shipping)" : "0"
  }
}, {
  "Ballast Idle" : "00:01",
  "Ballast LNG Cost" : "0",
  "Ballast LNG (m³)" : "0",
  "Ballast LNG (mmBtu)" : "0",
  "Ballast Cost" : "2,083",
  "Buy/Start Port" : "Punta Europa LNG",
  "Discharge/End Date" : "08/12/10",
  "Discharge/End Time" : "06:00",
  "Load/Event Duration" : "00:00",
  "Heel Cost" : "0",
  "Heel Revenue" : "0",
  "ID" : "Methane Lydon Volney",
  "L-ID" : "Methane Lydon Volney",
  "Load/Start Date" : "08/12/10",
  "Load/Start Time" : "06:00",
  "Next event date" : "08/12/10",
  "Next event port" : "Punta Europa LNG",
  "Addn. P&L" : "0",
  "P&L (Shipping)" : "-2,083",
  "P&L" : "-2,083",
  "P&L (Trading)" : "0",
  "P&L (Upstream)" : "0",
  "Scenario" : "/scenarios/sample-data/",
  "Bunker Cost" : "2,083",
  "Canal Cost" : "0",
  "Cooldown Cost" : "0",
  "Shipping Cost" : "2,083",
  "Shipping Entity" : "Shipping",
  "Hire Cost" : "0",
  "LNG Cost" : "0",
  "Other Cost" : "0",
  "Port Cost" : "0",
  "Total Cost" : "2,083",
  "Type" : "Start",
  "Vessel" : "Methane Lydon Volney (149k)",
  "[P&L]" : {
    "P&L (Shipping - Trading)" : "0",
    "P&L (Shipping - Shipping)" : "-2,083"
  }
}, {
  "Ballast Idle" : "00:00",
  "Ballast LNG Cost" : "0",
  "Ballast LNG (m³)" : "0",
  "Ballast LNG (mmBtu)" : "0",
  "Ballast Cost" : "0",
  "Buy/Start Port" : "Point Fortin",
  "Discharge/End Date" : "01/12/10",
  "Discharge/End Time" : "07:00",
  "Load/Event Duration" : "00:00",
  "Heel Cost" : "0",
  "Heel Revenue" : "0",
  "ID" : "Methane Princess",
  "L-ID" : "Methane Princess",
  "Load/Start Date" : "01/12/10",
  "Load/Start Time" : "07:00",
  "Next event date" : "01/12/10",
  "Next event port" : "Point Fortin",
  "Addn. P&L" : "0",
  "P&L (Shipping)" : "0",
  "P&L" : "0",
  "P&L (Trading)" : "0",
  "P&L (Upstream)" : "0",
  "Scenario" : "/scenarios/sample-data/",
  "Bunker Cost" : "0",
  "Canal Cost" : "0",
  "Cooldown Cost" : "0",
  "Shipping Cost" : "0",
  "Shipping Entity" : "Shipping",
  "Hire Cost" : "0",
  "LNG Cost" : "0",
  "Other Cost" : "0",
  "Port Cost" : "0",
  "Total Cost" : "0",
  "Type" : "Start",
  "Vessel" : "Methane Princess (138k)",
  "[P&L]" : {
    "P&L (Shipping - Trading)" : "0",
    "P&L (Shipping - Shipping)" : "0"
  }
}, {
  "Charter Rate" : "100,000",
  "Ballast Idle" : "23:12",
  "Ballast Travel" : "10:03",
  "Ballast LNG Cost" : "665,931",
  "Ballast LNG (m³)" : "4,172",
  "Ballast LNG (mmBtu)" : "95,133",
  "Ballast Speed" : "12.6",
  "Ballast Cost" : "4,158,431",
  "Buy Entity" : "US",
  "Buy Inco" : "FOB",
  "Purchase Cost" : "16,621,200",
  "Buy/Start Port" : "Point Fortin",
  "Buy Price" : "5.000",
  "Buy Volume" : "145,800",
  "Buy Volume (mmBtu)" : "3,324,240",
  "Cargo Type" : "Shipped",
  "D-ID" : "discharge-cargo-1",
  "Discharge Duration" : "01:00",
  "Discharge/End Date" : "11/01/11",
  "Discharge/End Time" : "14:00",
  "Discharge Window" : "11/01/11",
  "Load/Event Duration" : "01:00",
  "Heel Cost" : "0",
  "Heel Revenue" : "0",
  "ID" : "cargo-1",
  "L-ID" : "cargo-1",
  "Laden Idle" : "00:00",
  "Laden Travel" : "08:03",
  "Laden LNG Cost" : "468,728",
  "Laden LNG (m³)" : "2,936",
  "Laden LNG (mmBtu)" : "66,961",
  "Laden Speed" : "19.2",
  "Laden Cost" : "1,411,228",
  "Load/Start Date" : "02/01/11",
  "Load/Start Time" : "07:00",
  "Load/Start Window" : "02/01/11",
  "Next event date" : "15/02/11",
  "Next event port" : "Idku LNG",
  "Addn. P&L" : "0",
  "P&L (Shipping)" : "0",
  "P&L" : "1,078,820",
  "P&L (Trading)" : "1,078,820",
  "P&L (Upstream)" : "0",
  "Purchase Contract" : "HH Spot Purchase",
  "Sales Contract" : "NBP Sales",
  "Scenario" : "/scenarios/sample-data/",
  "Sell Entity" : "Europe",
  "Sell Inco" : "DES",
  "Sales Revenue" : "22,135,020",
  "Sell/End Port" : "Dragon LNG",
  "Sell Price" : "7.000",
  "Sell Volume" : "138,690",
  "Sell Volume (mmBtu)" : "3,162,145",
  "Bunker Cost" : "40,000",
  "Canal Cost" : "0",
  "Cooldown Cost" : "0",
  "Shipping Cost" : "4,435,000",
  "Shipping Entity" : "Shipping",
  "Hire Cost" : "4,375,000",
  "LNG Cost" : "0",
  "Other Cost" : "0",
  "Port Cost" : "20,000",
  "Total Cost" : "5,569,659",
  "Type" : "Cargo",
  "Vessel" : "Bluesky (145k)",
  "[P&L]" : {
    "P&L (Europe - Trading)" : "0",
    "P&L (Europe - Shipping)" : "0",
    "P&L (US - Trading)" : "1,078,820",
    "P&L (US - Shipping)" : "0"
  }
}, {
  "Ballast Idle" : "00:00",
  "Ballast Travel" : "15:03",
  "Ballast LNG Cost" : "543,611",
  "Ballast LNG (m³)" : "3,405",
  "Ballast LNG (mmBtu)" : "77,658",
  "Ballast Speed" : "18.0",
  "Ballast Cost" : "573,611",
  "Buy Entity" : "US",
  "Buy Inco" : "FOB",
  "Purchase Cost" : "19,323,000",
  "Buy/Start Port" : "Point Fortin",
  "Buy Price" : "5.000",
  "Buy Volume" : "169,500",
  "Buy Volume (mmBtu)" : "3,864,600",
  "Cargo Type" : "Shipped",
  "D-ID" : "discharge-cargo-12",
  "Discharge Duration" : "01:00",
  "Discharge/End Date" : "30/04/11",
  "Discharge/End Time" : "07:00",
  "Discharge Window" : "30/04/11",
  "Load/Event Duration" : "01:00",
  "Heel Cost" : "0",
  "Heel Revenue" : "0",
  "ID" : "cargo-12",
  "L-ID" : "cargo-12",
  "Laden Idle" : "00:00",
  "Laden Travel" : "15:23",
  "Laden LNG Cost" : "604,186",
  "Laden LNG (m³)" : "3,785",
  "Laden LNG (mmBtu)" : "86,311",
  "Laden Speed" : "17.9",
  "Laden Cost" : "634,187",
  "Load/Start Date" : "13/04/11",
  "Load/Start Time" : "07:00",
  "Load/Start Window" : "13/04/11",
  "Next event date" : "16/05/11",
  "Next event port" : "Punta Europa LNG",
  "Addn. P&L" : "0",
  "P&L (Shipping)" : "0",
  "P&L" : "6,521,401",
  "P&L (Trading)" : "6,521,401",
  "P&L (Upstream)" : "0",
  "Purchase Contract" : "HH Spot Purchase",
  "Sales Contract" : "JCC Sales",
  "Scenario" : "/scenarios/sample-data/",
  "Sell Entity" : "Asia",
  "Sell Inco" : "DES",
  "Sales Revenue" : "25,904,401",
  "Sell/End Port" : "Quintero Bay LNG",
  "Sell Price" : "7.000",
  "Sell Volume" : "162,308",
  "Sell Volume (mmBtu)" : "3,700,628",
  "Bunker Cost" : "40,000",
  "Canal Cost" : "0",
  "Cooldown Cost" : "0",
  "Shipping Cost" : "60,000",
  "Shipping Entity" : "Shipping",
  "Hire Cost" : "0",
  "LNG Cost" : "0",
  "Other Cost" : "0",
  "Port Cost" : "20,000",
  "Total Cost" : "1,207,797",
  "Type" : "Cargo",
  "Vessel" : "Methane Becki Anne (170k)",
  "[P&L]" : {
    "P&L (US - Trading)" : "6,521,401",
    "P&L (US - Shipping)" : "0",
    "P&L (Asia - Trading)" : "0",
    "P&L (Asia - Shipping)" : "0"
  }
}, {
  "Charter Rate" : "100,000",
  "Ballast Idle" : "00:00",
  "Ballast Travel" : "06:03",
  "Ballast Canal Entry" : "Suez Northside",
  "Ballast LNG Cost" : "348,007",
  "Ballast LNG (m³)" : "2,180",
  "Ballast LNG (mmBtu)" : "49,715",
  "Ballast Speed" : "19.5",
  "Ballast Cost" : "1,120,507",
  "Buy Entity" : "Asia",
  "Buy Inco" : "FOB",
  "Purchase Cost" : "15,732,000",
  "Buy/Start Port" : "Punta Europa LNG",
  "Buy Price" : "5.000",
  "Buy Volume" : "138,000",
  "Buy Volume (mmBtu)" : "3,146,400",
  "Cargo Type" : "Shipped",
  "D-ID" : "discharge-cargo-16",
  "Discharge Duration" : "01:00",
  "Discharge/End Date" : "30/04/11",
  "Discharge/End Time" : "07:00",
  "Discharge Window" : "30/04/11",
  "Load/Event Duration" : "01:00",
  "Heel Cost" : "0",
  "Heel Revenue" : "0",
  "ID" : "cargo-16",
  "L-ID" : "cargo-16",
  "Laden Idle" : "00:00",
  "Laden Travel" : "20:17",
  "Laden LNG Cost" : "720,400",
  "Laden LNG (m³)" : "4,513",
  "Laden LNG (mmBtu)" : "102,913",
  "Laden Speed" : "13.6",
  "Laden Cost" : "2,921,234",
  "Load/Start Date" : "08/04/11",
  "Load/Start Time" : "14:00",
  "Load/Start Window" : "08/04/11",
  "Next event date" : "07/05/11",
  "Next event port" : "Damietta",
  "Addn. P&L" : "0",
  "P&L (Shipping)" : "0",
  "P&L" : "2,251,057",
  "P&L (Trading)" : "2,251,057",
  "P&L (Upstream)" : "0",
  "Purchase Contract" : "JCC Spot Purchase",
  "Sales Contract" : "JCC Sales",
  "Scenario" : "/scenarios/sample-data/",
  "Sell Entity" : "Asia",
  "Sell Inco" : "DES",
  "Sales Revenue" : "20,956,390",
  "Sell/End Port" : "Hazira - LNG Terminal",
  "Sell Price" : "7.000",
  "Sell Volume" : "131,305",
  "Sell Volume (mmBtu)" : "2,993,770",
  "Bunker Cost" : "40,000",
  "Canal Cost" : "30,000",
  "Cooldown Cost" : "0",
  "Shipping Cost" : "2,973,333",
  "Shipping Entity" : "Shipping",
  "Hire Cost" : "2,883,333",
  "LNG Cost" : "0",
  "Other Cost" : "0",
  "Port Cost" : "20,000",
  "Total Cost" : "4,041,740",
  "Type" : "Cargo",
  "Vessel" : "Methane Princess (138k)",
  "[P&L]" : {
    "P&L (Asia - Trading)" : "2,251,057",
    "P&L (Asia - Shipping)" : "0"
  }
}, {
  "Charter Rate" : "100,000",
  "Ballast Idle" : "00:00",
  "Ballast Travel" : "13:12",
  "Ballast LNG Cost" : "767,037",
  "Ballast LNG (m³)" : "4,806",
  "Ballast LNG (mmBtu)" : "109,576",
  "Ballast Speed" : "19.5",
  "Ballast Cost" : "2,247,037",
  "Buy Entity" : "Asia",
  "Buy Inco" : "FOB",
  "Purchase Cost" : "15,732,000",
  "Buy/Start Port" : "Damietta",
  "Buy Price" : "5.000",
  "Buy Volume" : "138,000",
  "Buy Volume (mmBtu)" : "3,146,400",
  "Cargo Type" : "Shipped",
  "D-ID" : "discharge-cargo-20",
  "Discharge Duration" : "01:00",
  "Discharge/End Date" : "26/06/11",
  "Discharge/End Time" : "07:00",
  "Discharge Window" : "26/06/11",
  "Load/Event Duration" : "01:00",
  "Heel Cost" : "0",
  "Heel Revenue" : "0",
  "ID" : "cargo-20",
  "L-ID" : "cargo-20",
  "Laden Idle" : "01:18",
  "Laden Travel" : "20:06",
  "Laden LNG Cost" : "696,654",
  "Laden LNG (m³)" : "4,365",
  "Laden LNG (mmBtu)" : "99,522",
  "Laden Speed" : "13.0",
  "Laden Cost" : "3,026,654",
  "Load/Start Date" : "03/06/11",
  "Load/Start Time" : "14:00",
  "Load/Start Window" : "03/06/11",
  "Next event date" : "11/07/11",
  "Next event port" : "Damietta",
  "Addn. P&L" : "0",
  "P&L (Shipping)" : "0",
  "P&L" : "1,019,108",
  "P&L (Trading)" : "1,019,108",
  "P&L (Upstream)" : "0",
  "Purchase Contract" : "JCC Spot Purchase",
  "Sales Contract" : "HH Sales",
  "Scenario" : "/scenarios/sample-data/",
  "Sell Entity" : "US",
  "Sell Inco" : "DES",
  "Sales Revenue" : "20,561,108",
  "Sell/End Port" : "Pascagoula",
  "Sell Price" : "7.000",
  "Sell Volume" : "128,829",
  "Sell Volume (mmBtu)" : "2,937,301",
  "Bunker Cost" : "40,000",
  "Canal Cost" : "0",
  "Cooldown Cost" : "0",
  "Shipping Cost" : "3,810,000",
  "Shipping Entity" : "Shipping",
  "Hire Cost" : "3,750,000",
  "LNG Cost" : "0",
  "Other Cost" : "0",
  "Port Cost" : "20,000",
  "Total Cost" : "5,273,691",
  "Type" : "Cargo",
  "Vessel" : "Methane Princess (138k)",
  "[P&L]" : {
    "P&L (US - Trading)" : "0",
    "P&L (US - Shipping)" : "0",
    "P&L (Asia - Trading)" : "1,019,108",
    "P&L (Asia - Shipping)" : "0"
  }
}, {
  "Ballast Idle" : "00:15",
  "Ballast Travel" : "27:00",
  "Ballast LNG Cost" : "785,631",
  "Ballast LNG (m³)" : "4,922",
  "Ballast LNG (mmBtu)" : "112,233",
  "Ballast Speed" : "15.7",
  "Ballast Cost" : "815,631",
  "Buy Entity" : "Asia",
  "Buy Inco" : "FOB",
  "Purchase Cost" : "19,380,000",
  "Buy/Start Port" : "Punta Europa LNG",
  "Buy Price" : "5.000",
  "Buy Volume" : "170,000",
  "Buy Volume (mmBtu)" : "3,876,000",
  "Cargo Type" : "Shipped",
  "D-ID" : "discharge-cargo-21",
  "Discharge Duration" : "01:00",
  "Discharge/End Date" : "19/01/11",
  "Discharge/End Time" : "07:00",
  "Discharge Window" : "19/01/11",
  "Load/Event Duration" : "01:00",
  "Heel Cost" : "0",
  "Heel Revenue" : "0",
  "ID" : "cargo-21",
  "L-ID" : "cargo-21",
  "Laden Idle" : "03:02",
  "Laden Travel" : "24:07",
  "Laden LNG Cost" : "995,039",
  "Laden LNG (m³)" : "6,234",
  "Laden LNG (mmBtu)" : "142,148",
  "Laden Speed" : "17.5",
  "Laden Cost" : "1,025,039",
  "Load/Start Date" : "21/12/10",
  "Load/Start Time" : "14:00",
  "Load/Start Window" : "21/12/10",
  "Next event date" : "16/02/11",
  "Next event port" : "Punta Europa LNG",
  "Addn. P&L" : "0",
  "P&L (Shipping)" : "0",
  "P&L" : "5,831,529",
  "P&L (Trading)" : "5,831,529",
  "P&L (Upstream)" : "0",
  "Purchase Contract" : "JCC Spot Purchase",
  "Sales Contract" : "JCC Sales",
  "Scenario" : "/scenarios/sample-data/",
  "Sell Entity" : "Asia",
  "Sell Inco" : "DES",
  "Sales Revenue" : "25,271,529",
  "Sell/End Port" : "Pyeongtaek",
  "Sell Price" : "7.000",
  "Sell Volume" : "158,342",
  "Sell Volume (mmBtu)" : "3,610,218",
  "Bunker Cost" : "40,000",
  "Canal Cost" : "0",
  "Cooldown Cost" : "0",
  "Shipping Cost" : "60,000",
  "Shipping Entity" : "Shipping",
  "Hire Cost" : "0",
  "LNG Cost" : "0",
  "Other Cost" : "0",
  "Port Cost" : "20,000",
  "Total Cost" : "1,840,670",
  "Type" : "Cargo",
  "Vessel" : "Methane Julia Louise (170k)",
  "[P&L]" : {
    "P&L (Asia - Trading)" : "5,831,529",
    "P&L (Asia - Shipping)" : "0"
  }
}, {
  "Charter Rate" : "150,000",
  "Ballast Idle" : "00:00",
  "Ballast Travel" : "25:13",
  "Ballast LNG Cost" : "813,846",
  "Ballast LNG (m³)" : "5,098",
  "Ballast LNG (mmBtu)" : "116,263",
  "Ballast Speed" : "16.6",
  "Ballast Cost" : "4,825,096",
  "Buy Entity" : "Asia",
  "Buy Inco" : "FOB",
  "Purchase Cost" : "19,323,000",
  "Buy/Start Port" : "Idku LNG",
  "Buy Price" : "5.000",
  "Buy Volume" : "169,500",
  "Buy Volume (mmBtu)" : "3,864,600",
  "Cargo Type" : "Shipped",
  "D-ID" : "discharge-cargo-22",
  "Discharge Duration" : "01:00",
  "Discharge/End Date" : "18/03/11",
  "Discharge/End Time" : "09:00",
  "Discharge Window" : "07/03/11",
  "Load/Event Duration" : "01:00",
  "Heel Cost" : "0",
  "Heel Revenue" : "0",
  "ID" : "cargo-22",
  "L-ID" : "cargo-22",
  "Laden Idle" : "00:00",
  "Laden Travel" : "15:13",
  "Laden Canal Entry" : "Suez Northside",
  "Laden LNG Cost" : "719,330",
  "Laden LNG (m³)" : "4,506",
  "Laden LNG (mmBtu)" : "102,761",
  "Laden Speed" : "19.5",
  "Laden Cost" : "3,280,580",
  "Lateness" : "28d, 18h",
  "Load/Start Date" : "01/03/11",
  "Load/Start Time" : "13:00",
  "Load/Start Window" : "11/02/11",
  "Next event date" : "13/04/11",
  "Next event port" : "Punta Europa LNG",
  "Addn. P&L" : "0",
  "P&L (Shipping)" : "0",
  "P&L" : "-376,477",
  "P&L (Trading)" : "-376,477",
  "P&L (Upstream)" : "0",
  "Purchase Contract" : "JCC Spot Purchase",
  "Sales Contract" : "JCC Sales",
  "Scenario" : "/scenarios/sample-data/",
  "Sell Entity" : "Asia",
  "Sell Inco" : "DES",
  "Sales Revenue" : "25,519,022",
  "Sell/End Port" : "Pyeongtaek",
  "Sell Price" : "7.000",
  "Sell Volume" : "159,893",
  "Sell Volume (mmBtu)" : "3,645,574",
  "Bunker Cost" : "40,000",
  "Canal Cost" : "50,000",
  "Cooldown Cost" : "0",
  "Shipping Cost" : "6,572,500",
  "Shipping Entity" : "Shipping",
  "Hire Cost" : "6,462,500",
  "LNG Cost" : "0",
  "Other Cost" : "0",
  "Port Cost" : "20,000",
  "Total Cost" : "8,105,676",
  "Type" : "Cargo",
  "Vessel" : "Charter Ship (170k)",
  "[P&L]" : {
    "P&L (Asia - Trading)" : "-376,477",
    "P&L (Asia - Shipping)" : "0"
  }
}, {
  "Charter Rate" : "100,000",
  "Ballast Idle" : "03:05",
  "Ballast Travel" : "14:18",
  "Ballast LNG Cost" : "474,942",
  "Ballast LNG (m³)" : "2,975",
  "Ballast LNG (mmBtu)" : "67,848",
  "Ballast Speed" : "12.6",
  "Ballast Cost" : "2,400,775",
  "Buy Entity" : "US",
  "Buy Inco" : "FOB",
  "Purchase Cost" : "15,732,000",
  "Buy/Start Port" : "Point Fortin",
  "Buy Price" : "5.000",
  "Buy Volume" : "138,000",
  "Buy Volume (mmBtu)" : "3,146,400",
  "Cargo Type" : "Shipped",
  "D-ID" : "discharge-cargo-24",
  "Discharge Duration" : "01:00",
  "Discharge/End Date" : "04/01/11",
  "Discharge/End Time" : "14:00",
  "Discharge Window" : "04/01/11",
  "Load/Event Duration" : "01:00",
  "Heel Cost" : "0",
  "Heel Revenue" : "0",
  "ID" : "cargo-24",
  "L-ID" : "cargo-24",
  "Laden Idle" : "00:00",
  "Laden Travel" : "09:20",
  "Laden LNG Cost" : "479,325",
  "Laden LNG (m³)" : "3,002",
  "Laden LNG (mmBtu)" : "68,474",
  "Laden Speed" : "17.3",
  "Laden Cost" : "1,592,659",
  "Load/Start Date" : "24/12/10",
  "Load/Start Time" : "14:00",
  "Load/Start Window" : "24/12/10",
  "Next event date" : "23/01/11",
  "Next event port" : "Punta Europa LNG",
  "Addn. P&L" : "0",
  "P&L (Shipping)" : "0",
  "P&L" : "2,299,364",
  "P&L (Trading)" : "2,299,364",
  "P&L (Upstream)" : "0",
  "Purchase Contract" : "HH Spot Purchase",
  "Sales Contract" : "NBP Sales",
  "Scenario" : "/scenarios/sample-data/",
  "Sell Entity" : "Europe",
  "Sell Inco" : "DES",
  "Sales Revenue" : "21,070,531",
  "Sell/End Port" : "Isle of Grain",
  "Sell Price" : "7.000",
  "Sell Volume" : "132,020",
  "Sell Volume (mmBtu)" : "3,010,075",
  "Bunker Cost" : "40,000",
  "Canal Cost" : "0",
  "Cooldown Cost" : "0",
  "Shipping Cost" : "3,039,166",
  "Shipping Entity" : "Shipping",
  "Hire Cost" : "2,979,166",
  "LNG Cost" : "0",
  "Other Cost" : "0",
  "Port Cost" : "20,000",
  "Total Cost" : "3,993,433",
  "Type" : "Cargo",
  "Vessel" : "Methane Princess (138k)",
  "[P&L]" : {
    "P&L (Europe - Trading)" : "0",
    "P&L (Europe - Shipping)" : "0",
    "P&L (US - Trading)" : "2,299,364",
    "P&L (US - Shipping)" : "0"
  }
}, {
  "Ballast Idle" : "60:21",
  "Ballast Travel" : "31:15",
  "Ballast LNG Cost" : "1,880,088",
  "Ballast LNG (m³)" : "11,779",
  "Ballast LNG (mmBtu)" : "268,584",
  "Ballast Speed" : "12.6",
  "Ballast Cost" : "1,910,088",
  "Buy Entity" : "US",
  "Buy Inco" : "FOB",
  "Purchase Cost" : "17,065,800",
  "Buy/Start Port" : "Point Fortin",
  "Buy Price" : "5.000",
  "Buy Volume" : "149,700",
  "Buy Volume (mmBtu)" : "3,413,160",
  "Cargo Type" : "Shipped",
  "D-ID" : "discharge-cargo-28",
  "Discharge Duration" : "01:00",
  "Discharge/End Date" : "26/05/11",
  "Discharge/End Time" : "14:00",
  "Discharge Window" : "26/05/11",
  "Load/Event Duration" : "01:00",
  "Heel Cost" : "0",
  "Heel Revenue" : "0",
  "ID" : "cargo-28",
  "L-ID" : "cargo-28",
  "Laden Idle" : "00:00",
  "Laden Travel" : "30:13",
  "Laden LNG Cost" : "975,766",
  "Laden LNG (m³)" : "6,113",
  "Laden LNG (mmBtu)" : "139,394",
  "Laden Speed" : "13.0",
  "Laden Cost" : "1,005,767",
  "Load/Start Date" : "24/04/11",
  "Load/Start Time" : "13:00",
  "Load/Start Window" : "24/04/11",
  "Next event date" : "27/08/11",
  "Next event port" : "Point Fortin",
  "Addn. P&L" : "0",
  "P&L (Shipping)" : "0",
  "P&L" : "3,910,464",
  "P&L (Trading)" : "3,910,464",
  "P&L (Upstream)" : "0",
  "Purchase Contract" : "HH Spot Purchase",
  "Sales Contract" : "JCC Sales",
  "Scenario" : "/scenarios/sample-data/",
  "Sell Entity" : "Asia",
  "Sell Inco" : "DES",
  "Sales Revenue" : "21,036,264",
  "Sell/End Port" : "Fujian LNG",
  "Sell Price" : "7.000",
  "Sell Volume" : "131,806",
  "Sell Volume (mmBtu)" : "3,005,180",
  "Bunker Cost" : "40,000",
  "Canal Cost" : "0",
  "Cooldown Cost" : "0",
  "Shipping Cost" : "60,000",
  "Shipping Entity" : "Shipping",
  "Hire Cost" : "0",
  "LNG Cost" : "0",
  "Other Cost" : "0",
  "Port Cost" : "20,000",
  "Total Cost" : "2,915,854",
  "Type" : "Cargo",
  "Vessel" : "Methane Heather Sally (149k)",
  "[P&L]" : {
    "P&L (US - Trading)" : "3,910,464",
    "P&L (US - Shipping)" : "0",
    "P&L (Asia - Trading)" : "0",
    "P&L (Asia - Shipping)" : "0"
  }
}, {
  "Charter Rate" : "100,000",
  "Ballast Idle" : "54:13",
  "Ballast Travel" : "21:17",
  "Ballast LNG Cost" : "1,494,121",
  "Ballast LNG (m³)" : "9,361",
  "Ballast LNG (mmBtu)" : "213,445",
  "Ballast Speed" : "12.6",
  "Ballast Cost" : "9,249,120",
  "Buy Entity" : "Asia",
  "Buy Inco" : "FOB",
  "Purchase Cost" : "16,621,200",
  "Buy/Start Port" : "Punta Europa LNG",
  "Buy Price" : "5.000",
  "Buy Volume" : "145,800",
  "Buy Volume (mmBtu)" : "3,324,240",
  "Cargo Type" : "Shipped",
  "D-ID" : "discharge-cargo-30",
  "Discharge Duration" : "01:00",
  "Discharge/End Date" : "11/06/11",
  "Discharge/End Time" : "08:00",
  "Discharge Window" : "11/06/11",
  "Load/Event Duration" : "01:00",
  "Heel Cost" : "0",
  "Heel Revenue" : "0",
  "ID" : "cargo-30",
  "L-ID" : "cargo-30",
  "Laden Idle" : "00:01",
  "Laden Travel" : "20:23",
  "Laden LNG Cost" : "670,186",
  "Laden LNG (m³)" : "4,198",
  "Laden LNG (mmBtu)" : "95,740",
  "Laden Speed" : "13.0",
  "Laden Cost" : "2,900,185",
  "Load/Start Date" : "20/05/11",
  "Load/Start Time" : "13:00",
  "Load/Start Window" : "20/05/11",
  "Next event date" : "27/08/11",
  "Next event port" : "Punta Europa LNG",
  "Addn. P&L" : "0",
  "P&L (Shipping)" : "0",
  "P&L" : "-5,500,828",
  "P&L (Trading)" : "-5,500,828",
  "P&L (Upstream)" : "0",
  "Purchase Contract" : "JCC Spot Purchase",
  "Sales Contract" : "JCC Sales",
  "Scenario" : "/scenarios/sample-data/",
  "Sell Entity" : "Asia",
  "Sell Inco" : "DES",
  "Sales Revenue" : "21,105,371",
  "Sell/End Port" : "Quintero Bay LNG",
  "Sell Price" : "7.000",
  "Sell Volume" : "132,239",
  "Sell Volume (mmBtu)" : "3,015,053",
  "Bunker Cost" : "40,000",
  "Canal Cost" : "0",
  "Cooldown Cost" : "0",
  "Shipping Cost" : "9,984,998",
  "Shipping Entity" : "Shipping",
  "Hire Cost" : "9,924,998",
  "LNG Cost" : "0",
  "Other Cost" : "0",
  "Port Cost" : "20,000",
  "Total Cost" : "12,149,305",
  "Type" : "Cargo",
  "Vessel" : "Bluesky (145k)",
  "[P&L]" : {
    "P&L (Asia - Trading)" : "-5,500,828",
    "P&L (Asia - Shipping)" : "0"
  }
}, {
  "Charter Rate" : "100,000",
  "Ballast Idle" : "00:00",
  "Ballast Travel" : "13:08",
  "Ballast LNG Cost" : "757,567",
  "Ballast LNG (m³)" : "4,746",
  "Ballast LNG (mmBtu)" : "108,223",
  "Ballast Speed" : "19.5",
  "Ballast Cost" : "2,220,900",
  "Buy Entity" : "Europe",
  "Buy Inco" : "FOB",
  "Purchase Cost" : "15,732,000",
  "Buy/Start Port" : "Punta Europa LNG",
  "Buy Price" : "5.000",
  "Buy Volume" : "138,000",
  "Buy Volume (mmBtu)" : "3,146,400",
  "Cargo Type" : "Shipped",
  "D-ID" : "discharge-cargo-31",
  "Discharge Duration" : "01:00",
  "Discharge/End Date" : "07/03/11",
  "Discharge/End Time" : "07:00",
  "Discharge Window" : "07/03/11",
  "Load/Event Duration" : "01:00",
  "Heel Cost" : "0",
  "Heel Revenue" : "0",
  "ID" : "cargo-31",
  "L-ID" : "cargo-31",
  "Laden Idle" : "21:23",
  "Laden Travel" : "20:01",
  "Laden LNG Cost" : "1,270,548",
  "Laden LNG (m³)" : "7,960",
  "Laden LNG (mmBtu)" : "181,506",
  "Laden Speed" : "13.0",
  "Laden Cost" : "5,600,547",
  "Load/Start Date" : "23/01/11",
  "Load/Start Time" : "14:00",
  "Load/Start Window" : "23/01/11",
  "Next event date" : "21/03/11",
  "Next event port" : "Punta Europa LNG",
  "Addn. P&L" : "0",
  "P&L (Shipping)" : "0",
  "P&L" : "-1,528,650",
  "P&L (Trading)" : "-1,528,650",
  "P&L (Upstream)" : "0",
  "Purchase Contract" : "NBP Spot Purchase",
  "Sales Contract" : "JCC Sales",
  "Scenario" : "/scenarios/sample-data/",
  "Sell Entity" : "Asia",
  "Sell Inco" : "DES",
  "Sales Revenue" : "19,996,683",
  "Sell/End Port" : "Freeport LNG",
  "Sell Price" : "7.000",
  "Sell Volume" : "125,292",
  "Sell Volume (mmBtu)" : "2,856,669",
  "Bunker Cost" : "40,000",
  "Canal Cost" : "0",
  "Cooldown Cost" : "0",
  "Shipping Cost" : "5,793,332",
  "Shipping Entity" : "Shipping",
  "Hire Cost" : "5,733,332",
  "LNG Cost" : "0",
  "Other Cost" : "0",
  "Port Cost" : "20,000",
  "Total Cost" : "7,821,447",
  "Type" : "Cargo",
  "Vessel" : "Methane Princess (138k)",
  "[P&L]" : {
    "P&L (Europe - Trading)" : "-1,528,650",
    "P&L (Europe - Shipping)" : "0",
    "P&L (Asia - Trading)" : "0",
    "P&L (Asia - Shipping)" : "0"
  }
}, {
  "Charter Rate" : "150,000",
  "Ballast Idle" : "00:00",
  "Ballast Travel" : "15:13",
  "Ballast Canal Entry" : "Suez Northside",
  "Ballast LNG Cost" : "674,682",
  "Ballast LNG (m³)" : "4,226",
  "Ballast LNG (mmBtu)" : "96,383",
  "Ballast Speed" : "19.5",
  "Ballast Cost" : "3,215,932",
  "Buy Entity" : "Asia",
  "Buy Inco" : "FOB",
  "Purchase Cost" : "18,707,874",
  "Buy/Start Port" : "Punta Europa LNG",
  "Buy Price" : "5.000",
  "Buy Volume" : "164,104",
  "Buy Volume (mmBtu)" : "3,741,574",
  "Cargo Type" : "Shipped",
  "D-ID" : "discharge-cargo-32",
  "Discharge Duration" : "01:00",
  "Discharge/End Date" : "13/02/11",
  "Discharge/End Time" : "07:00",
  "Discharge Window" : "13/02/11",
  "Load/Event Duration" : "01:00",
  "Heel Cost" : "0",
  "Heel Revenue" : "0",
  "ID" : "cargo-32",
  "L-ID" : "cargo-32",
  "Laden Idle" : "18:02",
  "Laden Travel" : "24:07",
  "Laden LNG Cost" : "1,497,779",
  "Laden LNG (m³)" : "9,384",
  "Laden LNG (mmBtu)" : "213,968",
  "Laden Speed" : "17.5",
  "Laden Cost" : "8,034,029",
  "Load/Start Date" : "31/12/10",
  "Load/Start Time" : "14:00",
  "Load/Start Window" : "31/12/10",
  "Next event date" : "01/03/11",
  "Next event port" : "Idku LNG",
  "Addn. P&L" : "0",
  "P&L (Shipping)" : "0",
  "P&L" : "-2,905,636",
  "P&L (Trading)" : "-2,905,636",
  "P&L (Upstream)" : "0",
  "Purchase Contract" : "JCC Spot Purchase",
  "Sales Contract" : "JCC Sales",
  "Scenario" : "/scenarios/sample-data/",
  "Sell Entity" : "Asia",
  "Sell Inco" : "DES",
  "Sales Revenue" : "24,879,738",
  "Sell/End Port" : "Pyeongtaek",
  "Sell Price" : "7.000",
  "Sell Volume" : "155,888",
  "Sell Volume (mmBtu)" : "3,554,248",
  "Bunker Cost" : "40,000",
  "Canal Cost" : "30,000",
  "Cooldown Cost" : "0",
  "Shipping Cost" : "9,077,500",
  "Shipping Entity" : "Shipping",
  "Hire Cost" : "8,987,500",
  "LNG Cost" : "0",
  "Other Cost" : "0",
  "Port Cost" : "20,000",
  "Total Cost" : "11,249,961",
  "Type" : "Cargo",
  "Vessel" : "Charter Ship (170k)",
  "[P&L]" : {
    "P&L (Asia - Trading)" : "-2,905,636",
    "P&L (Asia - Shipping)" : "0"
  }
}, {
  "Ballast Idle" : "13:16",
  "Ballast Travel" : "22:16",
  "Ballast LNG Cost" : "869,287",
  "Ballast LNG (m³)" : "5,446",
  "Ballast LNG (mmBtu)" : "124,183",
  "Ballast Speed" : "12.6",
  "Ballast Cost" : "899,287",
  "Buy Entity" : "Asia",
  "Buy Inco" : "FOB",
  "Purchase Cost" : "17,065,800",
  "Buy/Start Port" : "Punta Europa LNG",
  "Buy Price" : "5.000",
  "Buy Volume" : "149,700",
  "Buy Volume (mmBtu)" : "3,413,160",
  "Cargo Type" : "Shipped",
  "D-ID" : "discharge-cargo-39",
  "Discharge Duration" : "01:00",
  "Discharge/End Date" : "01/01/11",
  "Discharge/End Time" : "07:00",
  "Discharge Window" : "01/01/11",
  "Load/Event Duration" : "01:00",
  "Heel Cost" : "0",
  "Heel Revenue" : "0",
  "ID" : "cargo-39",
  "L-ID" : "cargo-39",
  "Laden Idle" : "02:05",
  "Laden Travel" : "20:23",
  "Laden LNG Cost" : "732,430",
  "Laden LNG (m³)" : "4,588",
  "Laden LNG (mmBtu)" : "104,632",
  "Laden Speed" : "13.0",
  "Laden Cost" : "762,430",
  "Load/Start Date" : "08/12/10",
  "Load/Start Time" : "07:00",
  "Load/Start Window" : "08/12/10",
  "Next event date" : "07/02/11",
  "Next event port" : "Point Fortin",
  "Addn. P&L" : "0",
  "P&L (Shipping)" : "0",
  "P&L" : "5,164,601",
  "P&L (Trading)" : "5,164,601",
  "P&L (Upstream)" : "0",
  "Purchase Contract" : "JCC Spot Purchase",
  "Sales Contract" : "JCC Sales",
  "Scenario" : "/scenarios/sample-data/",
  "Sell Entity" : "Asia",
  "Sell Inco" : "DES",
  "Sales Revenue" : "22,290,401",
  "Sell/End Port" : "Quintero Bay LNG",
  "Sell Price" : "7.000",
  "Sell Volume" : "139,664",
  "Sell Volume (mmBtu)" : "3,184,343",
  "Bunker Cost" : "40,000",
  "Canal Cost" : "0",
  "Cooldown Cost" : "0",
  "Shipping Cost" : "60,000",
  "Shipping Entity" : "Shipping",
  "Hire Cost" : "0",
  "LNG Cost" : "0",
  "Other Cost" : "0",
  "Port Cost" : "20,000",
  "Total Cost" : "1,661,717",
  "Type" : "Cargo",
  "Vessel" : "Methane Lydon Volney (149k)",
  "[P&L]" : {
    "P&L (Asia - Trading)" : "5,164,601",
    "P&L (Asia - Shipping)" : "0"
  }
}, {
  "Charter Rate" : "100,000",
  "Ballast Idle" : "00:00",
  "Ballast Travel" : "18:00",
  "Ballast LNG Cost" : "526,900",
  "Ballast LNG (m³)" : "3,301",
  "Ballast LNG (mmBtu)" : "75,271",
  "Ballast Speed" : "12.7",
  "Ballast Cost" : "2,456,900",
  "Buy Entity" : "Asia",
  "Buy Inco" : "FOB",
  "Purchase Cost" : "16,621,200",
  "Buy/Start Port" : "Idku LNG",
  "Buy Price" : "5.000",
  "Buy Volume" : "145,800",
  "Buy Volume (mmBtu)" : "3,324,240",
  "Cargo Type" : "Shipped",
  "D-ID" : "discharge-cargo-41",
  "Discharge Duration" : "01:00",
  "Discharge/End Date" : "01/05/11",
  "Discharge/End Time" : "07:00",
  "Discharge Window" : "01/05/11",
  "Load/Event Duration" : "01:00",
  "Heel Cost" : "0",
  "Heel Revenue" : "0",
  "ID" : "cargo-41",
  "L-ID" : "cargo-41",
  "Laden Idle" : "11:07",
  "Laden Travel" : "17:17",
  "Laden LNG Cost" : "889,636",
  "Laden LNG (m³)" : "5,573",
  "Laden LNG (mmBtu)" : "127,090",
  "Laden Speed" : "13.0",
  "Laden Cost" : "3,919,635",
  "Load/Start Date" : "01/04/11",
  "Load/Start Time" : "14:00",
  "Load/Start Window" : "01/04/11",
  "Next event date" : "20/05/11",
  "Next event port" : "Punta Europa LNG",
  "Addn. P&L" : "0",
  "P&L (Shipping)" : "0",
  "P&L" : "271,942",
  "P&L (Trading)" : "271,942",
  "P&L (Upstream)" : "0",
  "Purchase Contract" : "JCC Spot Purchase",
  "Sales Contract" : "HH Sales",
  "Scenario" : "/scenarios/sample-data/",
  "Sell Entity" : "US",
  "Sell Inco" : "DES",
  "Sales Revenue" : "21,853,142",
  "Sell/End Port" : "Elba Island",
  "Sell Price" : "7.000",
  "Sell Volume" : "136,924",
  "Sell Volume (mmBtu)" : "3,121,877",
  "Bunker Cost" : "40,000",
  "Canal Cost" : "0",
  "Cooldown Cost" : "0",
  "Shipping Cost" : "4,959,999",
  "Shipping Entity" : "Shipping",
  "Hire Cost" : "4,899,999",
  "LNG Cost" : "0",
  "Other Cost" : "0",
  "Port Cost" : "20,000",
  "Total Cost" : "6,376,535",
  "Type" : "Cargo",
  "Vessel" : "Bluesky (145k)",
  "[P&L]" : {
    "P&L (US - Trading)" : "0",
    "P&L (US - Shipping)" : "0",
    "P&L (Asia - Trading)" : "271,942",
    "P&L (Asia - Shipping)" : "0"
  }
}, {
  "Ballast Idle" : "11:04",
  "Ballast Travel" : "24:03",
  "Ballast Canal Entry" : "Suez Northside",
  "Ballast LNG Cost" : "871,282",
  "Ballast LNG (m³)" : "5,458",
  "Ballast LNG (mmBtu)" : "124,468",
  "Ballast Speed" : "12.6",
  "Ballast Cost" : "931,282",
  "Buy Entity" : "US",
  "Buy Inco" : "FOB",
  "Purchase Cost" : "17,065,800",
  "Buy/Start Port" : "Point Fortin",
  "Buy Price" : "5.000",
  "Buy Volume" : "149,700",
  "Buy Volume (mmBtu)" : "3,413,160",
  "Cargo Type" : "Shipped",
  "D-ID" : "discharge-cargo-48",
  "Discharge Duration" : "01:00",
  "Discharge/End Date" : "15/03/11",
  "Discharge/End Time" : "07:00",
  "Discharge Window" : "15/03/11",
  "Load/Event Duration" : "01:00",
  "Heel Cost" : "0",
  "Heel Revenue" : "0",
  "ID" : "cargo-48",
  "L-ID" : "cargo-48",
  "Laden Idle" : "06:06",
  "Laden Travel" : "27:22",
  "Laden LNG Cost" : "1,070,649",
  "Laden LNG (m³)" : "6,708",
  "Laden LNG (mmBtu)" : "152,949",
  "Laden Speed" : "13.0",
  "Laden Cost" : "1,100,649",
  "Load/Start Date" : "07/02/11",
  "Load/Start Time" : "14:00",
  "Load/Start Window" : "07/02/11",
  "Next event date" : "20/04/11",
  "Next event port" : "Idku LNG",
  "Addn. P&L" : "0",
  "P&L (Shipping)" : "0",
  "P&L" : "4,794,387",
  "P&L (Trading)" : "4,794,387",
  "P&L (Upstream)" : "0",
  "Purchase Contract" : "HH Spot Purchase",
  "Sales Contract" : "JCC Sales",
  "Scenario" : "/scenarios/sample-data/",
  "Sell Entity" : "Asia",
  "Sell Inco" : "DES",
  "Sales Revenue" : "21,950,187",
  "Sell/End Port" : "Pyeongtaek",
  "Sell Price" : "7.000",
  "Sell Volume" : "137,532",
  "Sell Volume (mmBtu)" : "3,135,741",
  "Bunker Cost" : "40,000",
  "Canal Cost" : "30,000",
  "Cooldown Cost" : "0",
  "Shipping Cost" : "90,000",
  "Shipping Entity" : "Shipping",
  "Hire Cost" : "0",
  "LNG Cost" : "0",
  "Other Cost" : "0",
  "Port Cost" : "20,000",
  "Total Cost" : "2,031,931",
  "Type" : "Cargo",
  "Vessel" : "Methane Lydon Volney (149k)",
  "[P&L]" : {
    "P&L (US - Trading)" : "4,794,387",
    "P&L (US - Shipping)" : "0",
    "P&L (Asia - Trading)" : "0",
    "P&L (Asia - Shipping)" : "0"
  }
}, {
  "Ballast Idle" : "00:00",
  "Ballast Travel" : "14:18",
  "Ballast LNG Cost" : "587,310",
  "Ballast LNG (m³)" : "3,679",
  "Ballast LNG (mmBtu)" : "83,901",
  "Ballast Speed" : "15.6",
  "Ballast Cost" : "617,310",
  "Buy Entity" : "Asia",
  "Buy Inco" : "FOB",
  "Purchase Cost" : "17,065,800",
  "Buy/Start Port" : "Idku LNG",
  "Buy Price" : "5.000",
  "Buy Volume" : "149,700",
  "Buy Volume (mmBtu)" : "3,413,160",
  "Cargo Type" : "Shipped",
  "D-ID" : "discharge-cargo-5",
  "Discharge Duration" : "01:00",
  "Discharge/End Date" : "06/05/11",
  "Discharge/End Time" : "07:00",
  "Discharge Window" : "06/05/11",
  "Load/Event Duration" : "01:00",
  "Heel Cost" : "0",
  "Heel Revenue" : "0",
  "ID" : "cargo-5",
  "L-ID" : "cargo-5",
  "Laden Idle" : "00:00",
  "Laden Travel" : "15:07",
  "Laden LNG Cost" : "614,090",
  "Laden LNG (m³)" : "3,847",
  "Laden LNG (mmBtu)" : "87,726",
  "Laden Speed" : "15.1",
  "Laden Cost" : "644,091",
  "Load/Start Date" : "20/04/11",
  "Load/Start Time" : "07:00",
  "Load/Start Window" : "20/04/11",
  "Next event date" : "22/05/11",
  "Next event port" : "Punta Europa LNG",
  "Addn. P&L" : "0",
  "P&L (Shipping)" : "0",
  "P&L" : "5,564,918",
  "P&L (Trading)" : "5,564,918",
  "P&L (Upstream)" : "0",
  "Purchase Contract" : "JCC Spot Purchase",
  "Sales Contract" : "HH Sales",
  "Scenario" : "/scenarios/sample-data/",
  "Sell Entity" : "US",
  "Sell Inco" : "DES",
  "Sales Revenue" : "22,690,718",
  "Sell/End Port" : "Elba Island",
  "Sell Price" : "7.000",
  "Sell Volume" : "142,172",
  "Sell Volume (mmBtu)" : "3,241,531",
  "Bunker Cost" : "40,000",
  "Canal Cost" : "0",
  "Cooldown Cost" : "0",
  "Shipping Cost" : "60,000",
  "Shipping Entity" : "Shipping",
  "Hire Cost" : "0",
  "LNG Cost" : "0",
  "Other Cost" : "0",
  "Port Cost" : "20,000",
  "Total Cost" : "1,261,400",
  "Type" : "Cargo",
  "Vessel" : "Methane Lydon Volney (149k)",
  "[P&L]" : {
    "P&L (US - Trading)" : "0",
    "P&L (US - Shipping)" : "0",
    "P&L (Asia - Trading)" : "5,564,918",
    "P&L (Asia - Shipping)" : "0"
  }
}, {
  "Charter Rate" : "100,000",
  "Ballast Idle" : "02:04",
  "Ballast Travel" : "24:03",
  "Ballast Canal Entry" : "Suez Northside",
  "Ballast LNG Cost" : "727,642",
  "Ballast LNG (m³)" : "4,558",
  "Ballast LNG (mmBtu)" : "103,948",
  "Ballast Speed" : "12.6",
  "Ballast Cost" : "3,516,808",
  "Buy Entity" : "Asia",
  "Buy Inco" : "FOB",
  "Purchase Cost" : "16,621,200",
  "Buy/Start Port" : "Idku LNG",
  "Buy Price" : "5.000",
  "Buy Volume" : "145,800",
  "Buy Volume (mmBtu)" : "3,324,240",
  "Cargo Type" : "Shipped",
  "D-ID" : "discharge-cargo-50",
  "Discharge Duration" : "01:00",
  "Discharge/End Date" : "05/03/11",
  "Discharge/End Time" : "14:00",
  "Discharge Window" : "05/03/11",
  "Load/Event Duration" : "01:00",
  "Heel Cost" : "0",
  "Heel Revenue" : "0",
  "ID" : "cargo-50",
  "L-ID" : "cargo-50",
  "Laden Idle" : "00:00",
  "Laden Travel" : "17:00",
  "Laden Canal Entry" : "Suez Northside",
  "Laden LNG Cost" : "859,813",
  "Laden LNG (m³)" : "5,387",
  "Laden LNG (mmBtu)" : "122,830",
  "Laden Speed" : "17.8",
  "Laden Cost" : "2,739,813",
  "Load/Start Date" : "15/02/11",
  "Load/Start Time" : "07:00",
  "Load/Start Window" : "15/02/11",
  "Next event date" : "01/04/11",
  "Next event port" : "Idku LNG",
  "Addn. P&L" : "0",
  "P&L (Shipping)" : "0",
  "P&L" : "391,857",
  "P&L (Trading)" : "391,857",
  "P&L (Upstream)" : "0",
  "Purchase Contract" : "JCC Spot Purchase",
  "Sales Contract" : "JCC Sales",
  "Scenario" : "/scenarios/sample-data/",
  "Sell Entity" : "Asia",
  "Sell Inco" : "DES",
  "Sales Revenue" : "21,682,224",
  "Sell/End Port" : "Pyeongtaek",
  "Sell Price" : "7.000",
  "Sell Volume" : "135,853",
  "Sell Volume (mmBtu)" : "3,097,460",
  "Bunker Cost" : "40,000",
  "Canal Cost" : "80,000",
  "Cooldown Cost" : "0",
  "Shipping Cost" : "4,669,166",
  "Shipping Entity" : "Shipping",
  "Hire Cost" : "4,529,166",
  "LNG Cost" : "0",
  "Other Cost" : "0",
  "Port Cost" : "20,000",
  "Total Cost" : "6,256,621",
  "Type" : "Cargo",
  "Vessel" : "Bluesky (145k)",
  "[P&L]" : {
    "P&L (Asia - Trading)" : "391,857",
    "P&L (Asia - Shipping)" : "0"
  }
}, {
  "Ballast Idle" : "41:05",
  "Ballast Travel" : "18:02",
  "Ballast LNG Cost" : "1,177,182",
  "Ballast LNG (m³)" : "7,375",
  "Ballast LNG (mmBtu)" : "168,168",
  "Ballast Speed" : "15.7",
  "Ballast Cost" : "1,207,182",
  "Buy Entity" : "US",
  "Buy Inco" : "FOB",
  "Purchase Cost" : "19,323,000",
  "Buy/Start Port" : "Point Fortin",
  "Buy Price" : "5.000",
  "Buy Volume" : "169,500",
  "Buy Volume (mmBtu)" : "3,864,600",
  "Cargo Type" : "Shipped",
  "D-ID" : "discharge-cargo-60",
  "Discharge Duration" : "01:00",
  "Discharge/End Date" : "28/06/11",
  "Discharge/End Time" : "07:00",
  "Discharge Window" : "28/06/11",
  "Load/Event Duration" : "01:00",
  "Heel Cost" : "0",
  "Heel Revenue" : "0",
  "ID" : "cargo-60",
  "L-ID" : "cargo-60",
  "Laden Idle" : "04:11",
  "Laden Travel" : "16:06",
  "Laden LNG Cost" : "745,930",
  "Laden LNG (m³)" : "4,673",
  "Laden LNG (mmBtu)" : "106,561",
  "Laden Speed" : "17.5",
  "Laden Cost" : "775,930",
  "Load/Start Date" : "06/06/11",
  "Load/Start Time" : "14:00",
  "Load/Start Window" : "06/06/11",
  "Next event date" : "27/08/11",
  "Next event port" : "Point Fortin",
  "Addn. P&L" : "0",
  "P&L (Shipping)" : "0",
  "P&L" : "5,825,886",
  "P&L (Trading)" : "5,825,886",
  "P&L (Upstream)" : "0",
  "Purchase Contract" : "HH Spot Purchase",
  "Sales Contract" : "JCC Sales",
  "Scenario" : "/scenarios/sample-data/",
  "Sell Entity" : "Asia",
  "Sell Inco" : "DES",
  "Sales Revenue" : "25,208,886",
  "Sell/End Port" : "Quintero Bay LNG",
  "Sell Price" : "7.000",
  "Sell Volume" : "157,950",
  "Sell Volume (mmBtu)" : "3,601,269",
  "Bunker Cost" : "40,000",
  "Canal Cost" : "0",
  "Cooldown Cost" : "0",
  "Shipping Cost" : "60,000",
  "Shipping Entity" : "Shipping",
  "Hire Cost" : "0",
  "LNG Cost" : "0",
  "Other Cost" : "0",
  "Port Cost" : "20,000",
  "Total Cost" : "1,983,112",
  "Type" : "Cargo",
  "Vessel" : "Methane Julia Louise (170k)",
  "[P&L]" : {
    "P&L (US - Trading)" : "5,825,886",
    "P&L (US - Shipping)" : "0",
    "P&L (Asia - Trading)" : "0",
    "P&L (Asia - Shipping)" : "0"
  }
}, {
  "Ballast Idle" : "44:11",
  "Ballast Travel" : "26:09",
  "Ballast LNG Cost" : "1,467,255",
  "Ballast LNG (m³)" : "9,192",
  "Ballast LNG (mmBtu)" : "209,607",
  "Ballast Speed" : "15.7",
  "Ballast Cost" : "1,497,255",
  "Buy Entity" : "Asia",
  "Buy Inco" : "FOB",
  "Purchase Cost" : "19,323,000",
  "Buy/Start Port" : "Punta Europa LNG",
  "Buy Price" : "5.000",
  "Buy Volume" : "169,500",
  "Buy Volume (mmBtu)" : "3,864,600",
  "Cargo Type" : "Shipped",
  "D-ID" : "discharge-cargo-66",
  "Discharge Duration" : "01:00",
  "Discharge/End Date" : "17/06/11",
  "Discharge/End Time" : "07:00",
  "Discharge Window" : "17/06/11",
  "Load/Event Duration" : "01:00",
  "Heel Cost" : "0",
  "Heel Revenue" : "0",
  "ID" : "cargo-66",
  "L-ID" : "cargo-66",
  "Laden Idle" : "17:07",
  "Laden Travel" : "13:02",
  "Laden LNG Cost" : "1,059,809",
  "Laden LNG (m³)" : "6,640",
  "Laden LNG (mmBtu)" : "151,400",
  "Laden Speed" : "17.5",
  "Laden Cost" : "1,089,809",
  "Load/Start Date" : "16/05/11",
  "Load/Start Time" : "14:00",
  "Load/Start Window" : "16/05/11",
  "Next event date" : "27/08/11",
  "Next event port" : "Punta Europa LNG",
  "Addn. P&L" : "0",
  "P&L (Shipping)" : "0",
  "P&L" : "5,221,933",
  "P&L (Trading)" : "5,221,933",
  "P&L (Upstream)" : "0",
  "Purchase Contract" : "JCC Spot Purchase",
  "Sales Contract" : "JCC Sales",
  "Scenario" : "/scenarios/sample-data/",
  "Sell Entity" : "Asia",
  "Sell Inco" : "DES",
  "Sales Revenue" : "24,604,933",
  "Sell/End Port" : "Tobata",
  "Sell Price" : "7.000",
  "Sell Volume" : "154,166",
  "Sell Volume (mmBtu)" : "3,514,990",
  "Bunker Cost" : "40,000",
  "Canal Cost" : "0",
  "Cooldown Cost" : "0",
  "Shipping Cost" : "60,000",
  "Shipping Entity" : "Shipping",
  "Hire Cost" : "0",
  "LNG Cost" : "0",
  "Other Cost" : "0",
  "Port Cost" : "20,000",
  "Total Cost" : "2,587,064",
  "Type" : "Cargo",
  "Vessel" : "Methane Becki Anne (170k)",
  "[P&L]" : {
    "P&L (Asia - Trading)" : "5,221,933",
    "P&L (Asia - Shipping)" : "0"
  }
}, {
  "Ballast Idle" : "11:08",
  "Ballast Travel" : "23:23",
  "Ballast Canal Entry" : "Suez Northside",
  "Ballast LNG Cost" : "869,154",
  "Ballast LNG (m³)" : "5,445",
  "Ballast LNG (mmBtu)" : "124,164",
  "Ballast Speed" : "12.6",
  "Ballast Cost" : "929,154",
  "Buy Entity" : "Asia",
  "Buy Inco" : "FOB",
  "Purchase Cost" : "17,065,800",
  "Buy/Start Port" : "Punta Europa LNG",
  "Buy Price" : "5.000",
  "Buy Volume" : "149,700",
  "Buy Volume (mmBtu)" : "3,413,160",
  "Cargo Type" : "Shipped",
  "D-ID" : "discharge-cargo-70",
  "Discharge Duration" : "01:00",
  "Discharge/End Date" : "15/01/11",
  "Discharge/End Time" : "07:00",
  "Discharge Window" : "15/01/11",
  "Load/Event Duration" : "01:00",
  "Heel Cost" : "0",
  "Heel Revenue" : "0",
  "ID" : "cargo-70",
  "L-ID" : "cargo-70",
  "Laden Idle" : "12:23",
  "Laden Travel" : "32:17",
  "Laden LNG Cost" : "1,416,316",
  "Laden LNG (m³)" : "8,873",
  "Laden LNG (mmBtu)" : "202,330",
  "Laden Speed" : "13.0",
  "Laden Cost" : "1,446,316",
  "Load/Start Date" : "29/11/10",
  "Load/Start Time" : "07:00",
  "Load/Start Window" : "29/11/10",
  "Next event date" : "20/02/11",
  "Next event port" : "Damietta",
  "Addn. P&L" : "0",
  "P&L (Shipping)" : "0",
  "P&L" : "4,450,848",
  "P&L (Trading)" : "4,450,848",
  "P&L (Upstream)" : "0",
  "Purchase Contract" : "JCC Spot Purchase",
  "Sales Contract" : "JCC Sales",
  "Scenario" : "/scenarios/sample-data/",
  "Sell Entity" : "Asia",
  "Sell Inco" : "DES",
  "Sales Revenue" : "21,606,648",
  "Sell/End Port" : "Pyeongtaek",
  "Sell Price" : "7.000",
  "Sell Volume" : "135,380",
  "Sell Volume (mmBtu)" : "3,086,664",
  "Bunker Cost" : "40,000",
  "Canal Cost" : "30,000",
  "Cooldown Cost" : "0",
  "Shipping Cost" : "90,000",
  "Shipping Entity" : "Shipping",
  "Hire Cost" : "0",
  "LNG Cost" : "0",
  "Other Cost" : "0",
  "Port Cost" : "20,000",
  "Total Cost" : "2,375,470",
  "Type" : "Cargo",
  "Vessel" : "Methane Heather Sally (149k)",
  "[P&L]" : {
    "P&L (Asia - Trading)" : "4,450,848",
    "P&L (Asia - Shipping)" : "0"
  }
}, {
  "Ballast Idle" : "03:21",
  "Ballast Travel" : "24:10",
  "Ballast LNG Cost" : "763,287",
  "Ballast LNG (m³)" : "4,782",
  "Ballast LNG (mmBtu)" : "109,041",
  "Ballast Speed" : "15.7",
  "Ballast Cost" : "793,287",
  "Buy Entity" : "Asia",
  "Buy Inco" : "FOB",
  "Purchase Cost" : "19,323,000",
  "Buy/Start Port" : "Punta Europa LNG",
  "Buy Price" : "5.000",
  "Buy Volume" : "169,500",
  "Buy Volume (mmBtu)" : "3,864,600",
  "Cargo Type" : "Shipped",
  "D-ID" : "discharge-cargo-71",
  "Discharge Duration" : "01:00",
  "Discharge/End Date" : "17/03/11",
  "Discharge/End Time" : "07:00",
  "Discharge Window" : "17/03/11",
  "Load/Event Duration" : "01:00",
  "Heel Cost" : "0",
  "Heel Revenue" : "0",
  "ID" : "cargo-71",
  "L-ID" : "cargo-71",
  "Laden Idle" : "03:12",
  "Laden Travel" : "23:22",
  "Laden LNG Cost" : "995,238",
  "Laden LNG (m³)" : "6,235",
  "Laden LNG (mmBtu)" : "142,176",
  "Laden Speed" : "17.5",
  "Laden Cost" : "1,025,238",
  "Load/Start Date" : "16/02/11",
  "Load/Start Time" : "14:00",
  "Load/Start Window" : "16/02/11",
  "Next event date" : "15/04/11",
  "Next event port" : "Bonny Nigeria",
  "Addn. P&L" : "0",
  "P&L (Shipping)" : "0",
  "P&L" : "5,910,674",
  "P&L (Trading)" : "5,910,674",
  "P&L (Upstream)" : "0",
  "Purchase Contract" : "JCC Spot Purchase",
  "Sales Contract" : "JCC Sales",
  "Scenario" : "/scenarios/sample-data/",
  "Sell Entity" : "Asia",
  "Sell Inco" : "DES",
  "Sales Revenue" : "25,293,674",
  "Sell/End Port" : "Yung An",
  "Sell Price" : "7.000",
  "Sell Volume" : "158,481",
  "Sell Volume (mmBtu)" : "3,613,382",
  "Bunker Cost" : "40,000",
  "Canal Cost" : "0",
  "Cooldown Cost" : "0",
  "Shipping Cost" : "60,000",
  "Shipping Entity" : "Shipping",
  "Hire Cost" : "0",
  "LNG Cost" : "0",
  "Other Cost" : "0",
  "Port Cost" : "20,000",
  "Total Cost" : "1,818,525",
  "Type" : "Cargo",
  "Vessel" : "Methane Julia Louise (170k)",
  "[P&L]" : {
    "P&L (Asia - Trading)" : "5,910,674",
    "P&L (Asia - Shipping)" : "0"
  }
}, {
  "Ballast Idle" : "27:22",
  "Ballast Travel" : "34:15",
  "Ballast LNG Cost" : "1,440,256",
  "Ballast LNG (m³)" : "9,023",
  "Ballast LNG (mmBtu)" : "205,750",
  "Ballast Speed" : "12.6",
  "Ballast Cost" : "1,470,256",
  "Buy Entity" : "Asia",
  "Buy Inco" : "FOB",
  "Purchase Cost" : "17,065,800",
  "Buy/Start Port" : "Punta Europa LNG",
  "Buy Price" : "5.000",
  "Buy Volume" : "149,700",
  "Buy Volume (mmBtu)" : "3,413,160",
  "Cargo Type" : "Shipped",
  "D-ID" : "discharge-cargo-76",
  "Discharge Duration" : "01:00",
  "Discharge/End Date" : "25/06/11",
  "Discharge/End Time" : "14:00",
  "Discharge Window" : "25/06/11",
  "Load/Event Duration" : "01:00",
  "Heel Cost" : "0",
  "Heel Revenue" : "0",
  "ID" : "cargo-76",
  "L-ID" : "cargo-76",
  "Laden Idle" : "00:00",
  "Laden Travel" : "32:23",
  "Laden LNG Cost" : "1,082,643",
  "Laden LNG (m³)" : "6,782",
  "Laden LNG (mmBtu)" : "154,662",
  "Laden Speed" : "13.2",
  "Laden Cost" : "1,112,644",
  "Load/Start Date" : "22/05/11",
  "Load/Start Time" : "07:00",
  "Load/Start Window" : "22/05/11",
  "Next event date" : "27/08/11",
  "Next event port" : "Punta Europa LNG",
  "Addn. P&L" : "0",
  "P&L (Shipping)" : "0",
  "P&L" : "4,243,419",
  "P&L (Trading)" : "4,243,419",
  "P&L (Upstream)" : "0",
  "Purchase Contract" : "JCC Spot Purchase",
  "Sales Contract" : "JCC Sales",
  "Scenario" : "/scenarios/sample-data/",
  "Sell Entity" : "Asia",
  "Sell Inco" : "DES",
  "Sales Revenue" : "21,369,219",
  "Sell/End Port" : "Ogishima - Tokyo Gas LNG Berth",
  "Sell Price" : "7.000",
  "Sell Volume" : "133,892",
  "Sell Volume (mmBtu)" : "3,052,745",
  "Bunker Cost" : "40,000",
  "Canal Cost" : "0",
  "Cooldown Cost" : "0",
  "Shipping Cost" : "60,000",
  "Shipping Entity" : "Shipping",
  "Hire Cost" : "0",
  "LNG Cost" : "0",
  "Other Cost" : "0",
  "Port Cost" : "20,000",
  "Total Cost" : "2,582,899",
  "Type" : "Cargo",
  "Vessel" : "Methane Lydon Volney (149k)",
  "[P&L]" : {
    "P&L (Asia - Trading)" : "4,243,419",
    "P&L (Asia - Shipping)" : "0"
  }
}, {
  "Ballast Idle" : "00:00",
  "Ballast Travel" : "05:05",
  "Ballast LNG Cost" : "153,761",
  "Ballast LNG (m³)" : "962",
  "Ballast LNG (mmBtu)" : "21,965",
  "Ballast Speed" : "12.8",
  "Ballast Cost" : "183,761",
  "Buy Entity" : "Asia",
  "Buy Inco" : "FOB",
  "Purchase Cost" : "17,065,800",
  "Buy/Start Port" : "Damietta",
  "Buy Price" : "5.000",
  "Buy Volume" : "149,700",
  "Buy Volume (mmBtu)" : "3,413,160",
  "Violation" : "1",
  "Cargo Type" : "Shipped",
  "D-ID" : "discharge-cargo-78",
  "Discharge Duration" : "01:00",
  "Discharge/End Date" : "18/04/11",
  "Discharge/End Time" : "07:00",
  "Discharge Window" : "18/04/11",
  "Load/Event Duration" : "01:00",
  "Heel Cost" : "0",
  "Heel Revenue" : "0",
  "ID" : "cargo-78",
  "L-ID" : "cargo-78",
  "Laden Idle" : "07:09",
  "Laden Travel" : "17:22",
  "Laden LNG Cost" : "783,768",
  "Laden LNG (m³)" : "4,910",
  "Laden LNG (mmBtu)" : "111,966",
  "Laden Speed" : "13.0",
  "Laden Cost" : "813,768",
  "Load/Start Date" : "23/03/11",
  "Load/Start Time" : "07:00",
  "Load/Start Window" : "23/03/11",
  "Next event date" : "24/04/11",
  "Next event port" : "Point Fortin",
  "Addn. P&L" : "0",
  "P&L (Shipping)" : "0",
  "P&L" : "5,828,789",
  "P&L (Trading)" : "5,828,789",
  "P&L (Upstream)" : "0",
  "Purchase Contract" : "JCC Spot Purchase",
  "Sales Contract" : "HH Sales",
  "Scenario" : "/scenarios/sample-data/",
  "Sell Entity" : "US",
  "Sell Inco" : "DES",
  "Sales Revenue" : "22,954,589",
  "Sell/End Port" : "Elba Island",
  "Sell Price" : "7.000",
  "Sell Volume" : "143,825",
  "Sell Volume (mmBtu)" : "3,279,227",
  "Bunker Cost" : "40,000",
  "Canal Cost" : "0",
  "Cooldown Cost" : "0",
  "Shipping Cost" : "60,000",
  "Shipping Entity" : "Shipping",
  "Hire Cost" : "0",
  "LNG Cost" : "0",
  "Other Cost" : "0",
  "Port Cost" : "20,000",
  "Total Cost" : "997,529",
  "Type" : "Cargo",
  "Vessel" : "Methane Heather Sally (149k)",
  "[P&L]" : {
    "P&L (US - Trading)" : "0",
    "P&L (US - Shipping)" : "0",
    "P&L (Asia - Trading)" : "5,828,789",
    "P&L (Asia - Shipping)" : "0"
  }
}, {
  "Charter Rate" : "150,000",
  "Ballast Idle" : "10:21",
  "Ballast Travel" : "24:10",
  "Ballast LNG Cost" : "875,007",
  "Ballast LNG (m³)" : "5,482",
  "Ballast LNG (mmBtu)" : "125,001",
  "Ballast Speed" : "15.7",
  "Ballast Cost" : "6,348,757",
  "Buy Entity" : "Asia",
  "Buy Inco" : "FOB",
  "Purchase Cost" : "19,323,000",
  "Buy/Start Port" : "Punta Europa LNG",
  "Buy Price" : "5.000",
  "Buy Volume" : "169,500",
  "Buy Volume (mmBtu)" : "3,864,600",
  "Cargo Type" : "Shipped",
  "D-ID" : "discharge-cargo-9",
  "Discharge Duration" : "01:00",
  "Discharge/End Date" : "10/05/11",
  "Discharge/End Time" : "07:00",
  "Discharge Window" : "10/05/11",
  "Load/Event Duration" : "01:00",
  "Heel Cost" : "0",
  "Heel Revenue" : "0",
  "ID" : "cargo-9",
  "L-ID" : "cargo-9",
  "Laden Idle" : "01:12",
  "Laden Travel" : "23:22",
  "Laden LNG Cost" : "928,206",
  "Laden LNG (m³)" : "5,815",
  "Laden LNG (mmBtu)" : "132,600",
  "Laden Speed" : "17.5",
  "Laden Cost" : "4,920,706",
  "Load/Start Date" : "13/04/11",
  "Load/Start Time" : "14:00",
  "Load/Start Window" : "13/04/11",
  "Next event date" : "15/06/11",
  "Next event port" : "Bonny Nigeria",
  "Addn. P&L" : "0",
  "P&L (Shipping)" : "0",
  "P&L" : "-3,540,263",
  "P&L (Trading)" : "-3,540,263",
  "P&L (Upstream)" : "0",
  "Purchase Contract" : "JCC Spot Purchase",
  "Sales Contract" : "JCC Sales",
  "Scenario" : "/scenarios/sample-data/",
  "Sell Entity" : "Asia",
  "Sell Inco" : "DES",
  "Sales Revenue" : "25,248,986",
  "Sell/End Port" : "Yung An",
  "Sell Price" : "7.000",
  "Sell Volume" : "158,201",
  "Sell Volume (mmBtu)" : "3,606,998",
  "Bunker Cost" : "40,000",
  "Canal Cost" : "0",
  "Cooldown Cost" : "0",
  "Shipping Cost" : "9,466,250",
  "Shipping Entity" : "Shipping",
  "Hire Cost" : "9,406,250",
  "LNG Cost" : "0",
  "Other Cost" : "0",
  "Port Cost" : "20,000",
  "Total Cost" : "11,269,463",
  "Type" : "Cargo",
  "Vessel" : "Charter Ship (170k)",
  "[P&L]" : {
    "P&L (Asia - Trading)" : "-3,540,263",
    "P&L (Asia - Shipping)" : "0"
  }
} ]